{
  "paragraphs": [
    {
      "text": "val parquetFileClick \u003d sqlContext.read.parquet(\"/home/ama/sidana/calypso_data_may_june/calypso_data_may_june/click/nb/2016/*/*/*.parquet\")\nval offerView \u003d parquetFileClick(\"offerViewId\")\nval offer \u003d substring_index(offerView,\"-\",1)\n//val uniqueOffers \u003d parquetFileClick[$\"offerViewId\"].substring_index(\"offerViewId\", \"-\", 1)\n",
      "authenticationInfo": {},
      "dateUpdated": "Jul 3, 2016 6:54:24 PM",
      "config": {
        "colWidth": 12.0,
        "graph": {
          "mode": "table",
          "height": 300.0,
          "optionOpen": false,
          "keys": [],
          "values": [],
          "groups": [],
          "scatter": {}
        },
        "enabled": true,
        "editorMode": "ace/mode/scala"
      },
      "settings": {
        "params": {},
        "forms": {}
      },
      "jobName": "paragraph_1467476100547_477450148",
      "id": "20160702-181500_1334300339",
      "result": {
        "code": "SUCCESS",
        "type": "TEXT",
        "msg": "parquetFileClick: org.apache.spark.sql.DataFrame \u003d [userId: string, ip: string, userAgent: struct\u003cdeviceType:string,operatingSystem:string,browser:string,rawUserAgent:string\u003e, geolocation: struct\u003ccountry:string,countryCode:string,state:string,city:string,timeZone:string\u003e, siteDomain: struct\u003ccountryCode:string,domainName:string\u003e, dataCenter: string, utcDate: timestamp, offerTitle: string, category: array\u003cstring\u003e, price: decimal(38,18), merchant: string, source: string, keywords: array\u003cstring\u003e, offerViewId: string, clickId: string, earning: decimal(38,18)]\nofferView: org.apache.spark.sql.Column \u003d offerViewId\noffer: org.apache.spark.sql.Column \u003d substring_index(offerViewId,-,1)\n"
      },
      "dateCreated": "Jul 2, 2016 6:15:00 PM",
      "dateStarted": "Jul 3, 2016 6:54:24 PM",
      "dateFinished": "Jul 3, 2016 6:54:26 PM",
      "status": "FINISHED",
      "progressUpdateIntervalMs": 500
    },
    {
      "text": "val parquetFileClick \u003d sqlContext.read.parquet(\"/home/ama/sidana/calypso_data_may_june/calypso_data_may_june/click/nb/2016/*/*/*.parquet\")\nval offerViewId \u003d parquetFileClick.select(\"offerViewId\")\nval offerId \u003d parquetFileClick.select(substring_index(parquetFileClick(\"offerViewId\"),\"-\",1))",
      "authenticationInfo": {},
      "dateUpdated": "Oct 18, 2016 5:40:45 PM",
      "config": {
        "colWidth": 12.0,
        "graph": {
          "mode": "table",
          "height": 300.0,
          "optionOpen": false,
          "keys": [],
          "values": [],
          "groups": [],
          "scatter": {}
        },
        "enabled": true,
        "editorMode": "ace/mode/scala"
      },
      "settings": {
        "params": {},
        "forms": {}
      },
      "jobName": "paragraph_1467564319342_-1636326888",
      "id": "20160703-184519_2083546828",
      "result": {
        "code": "SUCCESS",
        "type": "TEXT",
        "msg": "parquetFileClick: org.apache.spark.sql.DataFrame \u003d [userId: string, ip: string, userAgent: struct\u003cdeviceType:string,operatingSystem:string,browser:string,rawUserAgent:string\u003e, geolocation: struct\u003ccountry:string,countryCode:string,state:string,city:string,timeZone:string\u003e, siteDomain: struct\u003ccountryCode:string,domainName:string\u003e, dataCenter: string, utcDate: timestamp, offerTitle: string, category: array\u003cstring\u003e, price: decimal(38,18), merchant: string, source: string, keywords: array\u003cstring\u003e, offerViewId: string, clickId: string, earning: decimal(38,18)]\nofferViewId: org.apache.spark.sql.DataFrame \u003d [offerViewId: string]\nofferId: org.apache.spark.sql.DataFrame \u003d [substring_index(offerViewId,-,1): string]\n"
      },
      "dateCreated": "Jul 3, 2016 6:45:19 PM",
      "dateStarted": "Jul 3, 2016 9:40:20 PM",
      "dateFinished": "Jul 3, 2016 9:40:21 PM",
      "status": "FINISHED",
      "progressUpdateIntervalMs": 500
    },
    {
      "text": "z.show(offerViewId)",
      "authenticationInfo": {},
      "dateUpdated": "Oct 13, 2016 9:16:31 PM",
      "config": {
        "colWidth": 12.0,
        "graph": {
          "mode": "table",
          "height": 300.0,
          "optionOpen": false,
          "keys": [],
          "values": [],
          "groups": [],
          "scatter": {}
        },
        "enabled": true,
        "editorMode": "ace/mode/scala"
      },
      "settings": {
        "params": {},
        "forms": {}
      },
      "jobName": "paragraph_1467574709765_-585684231",
      "id": "20160703-213829_175473542",
      "result": {
        "code": "SUCCESS",
        "type": "TABLE",
        "msg": "offerViewId\n5d3676b24a4fc54578cf2fd73b00cfb1-1076982525550_1462122723002_44467\n201c12fd658faa802f35db6da9ade2a8-1076982041554_1462099282360_13096\n9af4a10e737255532e69bc08823cf820-10769813923902_1462100414458_13981\nnull\nnull\nd9594eda16a5e2ec1e34b424afd2703e-10769812113194_1462128854647_56868\nd9594eda16a5e2ec1e34b424afd2703e-10769812113194_1462128854647_56868\nca6cac2d6b4168bb7b320dcedcfdae5d-10769812113194_1462101948466_15468\nnull\nnull\n85d16a679bc1f272429ea57a27d76304-10769825327059_1462104395298_17552\nnull\nnull\n3358b3f0332ad2ccf1795ab6ba1b2bad-10769812113194_1462132037613_64297\nbc9b163edd4d5327be9d961b0b2e1986-10769813923902_1462133748067_69431\nbc9b163edd4d5327be9d961b0b2e1986-10769813923902_1462133748067_69431\nnull\nnull\nnull\nnull\nnull\nnull\nnull\n2beae2f482dc031732010cd1c583c86d-1076984112404_1462104885645_18031\n11ef2eba8ba8bdad00ab87ad0d6f7109-10769825327059_1462120373748_40212\n2fa324819ba9fdc5c28a74356799c049-1076982041554_1462103579358_16826\n5cd850dfb0fd858d21623cbcdd0de4e5-10769825327059_1462122109751_42400\nnull\nae3d43fc2f70c2521d544965ace6129e-10769812113194_1462093046998_7442\nc5fbe45650e3fae7c2d60d461f80fc14-1076982504506_1462129096427_57432\nab06a0a98c45f27ae0aee1ef792dfbe8-1076984112404_1462101848581_15260\n595f35fe3de601a72d68b12b447e2560-10769812113194_1462107631643_20516\nbc4c23ec458e902de84e035ec18a04be-1076984112404_1462107177049_20084\nnull\n3032c3a83aa0f588e1c02791fa3a628b-1076984112404_1462118879337_36606\nnull\n0cd791e39646070913b7c20899ee211b-10769813923902_1462132157176_64423\n58488a145186eb49e0cac648651344de-1076982525550_1462133421288_69105\nc76e2d9a61fc563747246ec7c605b27b-1076982525550_1462123423551_46856\n7196b23750d29ef7f7378a55671fbb86-10769825327059_1462107287820_20129\ncac10f0f471f17e66c4eb62e497fdfb1-10769812113194_1462133791876_69513\n0c5430549bd2d7ca9f1a9ccc03ca6f17-1076982041554_1462140325285_78929\nnull\n779ed718b1811d8ca059f33b8c0daa20-1076982504506_1462106274382_19541\n0c06820b06e3e684771a4ee2ae47bf5b-1076982041554_1462089223000_4227\nbdc8aa301e98347b50277ff8dae93950-1076982041554_1462103074055_16367\n02ab810a9e666af7a58bb576346b5016-1076982041554_1462086668248_2643\nnull\n6bcfdf04a206b3ae60c417d5d98b1b49-1076982041554_1462111197241_23629\n6bcfdf04a206b3ae60c417d5d98b1b49-1076982041554_1462111197241_23629\n6bcfdf04a206b3ae60c417d5d98b1b49-1076982041554_1462111197241_23629\n600823cc1779f707dfd20c47e0eb39a1-1076982041554_1462100663790_14259\n8eaad66df52786d6a25508fe320be7e8-10769812113194_1462125297898_49070\n50bd10ae4625fb78e26d613138983389-10769825327059_1462132273046_64503\nnull\nnull\nnull\nnull\nnull\nnull\nnull\nnull\n2db1608d77e0227cebdcb18a0d626058-1076982504506_1462131352890_63700\n0db22d3180be67d3ce11f8c9f59ee073-1076982514043_1462109346541_22168\nnull\ne6d91eaab409f4b6f06fcbf3183cd3e2-1076982504506_1462082512817_860\na4afda6722ccbbc584331a915454849e-10769825227166_1462075617699_92243\nabedcc442b42bae493ae8c00cb39f20f-10769812113194_1462127405226_54916\nnull\n08b458dde3ed54c65660f39741cf5e39-1076982041554_1462090415852_5138\nnull\n55cd134343777481ab26deade6ea62aa-1076982525550_1462104402625_17721\nnull\nc6ff34a6d631d637ea52458eb98e2514-1076982041554_1462110831071_23315\nnull\nnull\n37539e831ddfdca100ad0f8d39e07276-1076982041554_1462114154880_27963\nnull\n57231353f47b0291462de4ec6221259a-1076982525550_1462127722863_55441\n57231353f47b0291462de4ec6221259a-1076982525550_1462127722863_55441\nc2d8c72aa369ef0ef7d4bab511d69589-1076982504506_1462107785149_20838\na267c0e4992d68eb7907b2000687599a-10769825327059_1462093225334_7604\n08b458dde3ed54c65660f39741cf5e39-10769813923902_1462131544617_63610\n754483dd310231d1c0dc86f0c807b44c-1076982504506_1462091347642_6116\nbbe7b50850acbd73e2b10ec24ebba294-1076982504506_1462116522220_33416\n5c9319ddb5db134ca3d3e5d17ef0e115-1076982504506_1462091456624_6192\n9f1f66e132203ba060cf8951eef52b94-1076982504506_1462099884849_13827\nnull\nnull\nnull\n75e29fae3fb5374c275c5998400f7b2b-10769825327059_1462104300244_17461\nf42ebbf9a5885faaf3faca09e20daf95-1076982514043_1462125813692_50115\n9dc3eb2c84def8fe041d93e6e3ae1a26-1076981397106_1462070277727_91235\n7bc7a074188aaa1761af43bbdd0a0ba9-1076982504506_1462107034526_20190\n5e0f9a31e5aa523e06f043accd795d23-10769825327059_1462120264925_40109\nnull\nnull\nfc674c68722305d350ad74050ac81d00-10769825327059_1462103238670_16457\nnull\n735f50f627bae1805a846379c7417a99-1076982514043_1462080122064_223\nnull\n63c19b5b0183f828fcd7472578b9c4c8-1076982514043_1462102531953_16049\n5084d0f7bc1edb911d6fd86a18649ac6-1076982504506_1462130525977_62644\n2a0b781a77ecb6441fc793e36d6bdd3e-1076982504506_1462131233078_63550\nc13bdc5a48274bad00f6d33f598d5ccf-10769813923902_1462140544519_79070\nnull\n2fdb297c9b11e933f5c10d59f5b84027-1076982504506_1462127511764_55336\n2fdb297c9b11e933f5c10d59f5b84027-1076982504506_1462127511764_55336\nadfde0c4f3d7316e177f67571f65d6c7-1076984112404_1462104169922_17346\n6bb33f3e628e07d353fcf17c526758ca-1076984112404_1462095520981_9541\n13492098a67300530969caf18a1852b2-10769813923902_1462093159329_7443\nnull\nb5c9376dfb1955207918ee4cb02f171b-10769812113194_1462118470811_35475\nnull\nnull\nnull\nnull\n0110a549147ef65a3448b2c150c29da9-1076982504506_1462130196608_62189\ne33a2d4a0c64959dfd33177ce450dcb8-10769820411854_1462064499183_90292\n4f065187cde3d6259bc157d1d99bdcbf-10769825327059_1462132490399_64824\nnull\n22fac07a44fc1b5cd01ed1ace279f70a-10769812113194_1462125684727_49619\nnull\nnull\nnull\na8db965efbb53c12b90c984e6d6a0b7b-1076982514043_1462105891724_19099\nba9d79b41170ba174c7d61282810f0aa-1076984112404_1462110469981_23013\nnull\n2db55b1344f460bc7be3ab61d86f707d-10769812113194_1462117165107_33946\nd10b00873f60618be17b5ae5645e05e1-1076984112404_1462114204086_27963\n44f0916c480e153bf4ba9d3dcaad1108-10769825327059_1462115532491_30832\n00f0aeb67879cbd9785f442cc549f816-1076984112404_1462093509040_7753\naa3b0faece6e16380e02367b2afdd0e1-1076982514043_1462087001132_3016\nf818256487d6935c573d1560376e8444-10769813923902_1462092687329_6999\n2bfd92ccfd38430fe5d7eff19aa2b283-10769813923902_1462107728545_20455\nnull\naa3775a98577fb817e110914865e91f0-1076982514043_1462124002129_47709\n9f2c085c101a79c78284d172876d4295-1076982504506_1462086125576_2582\n20027090a09114cc35d44d650d9a09c6-1076982514043_1462133604303_69432\n20027090a09114cc35d44d650d9a09c6-1076982514043_1462133604303_69432\n6da7c52d1147d9c651a6e0b743a5d889-1076982525550_1462135750070_71778\n6ff08d322cf2fe4666f153f7b345eb5e-1076982525550_1462094081713_8434\n4a2b77dfdd9c6b01b6a8b84566975ccc-1076984112404_1462104030548_17182\ne33d7218e4975b4631cb14907cf3aa4c-10769825327059_1462104333620_17490\n83dc8cb4d59f9d959bcb7453cf17d82b-1076982504506_1462091347642_6116\n82331583a2b02ef1c55b5a4f24937b6e-1076984111443_1462066123185_90486\nnull\nd6d05dd790d686d6857151d5e6e4fbf8-10769812113194_1462086127942_2413\nnull\nnull\nc81e491f1405bbffb3b873ee3d83e053-1076982041554_1462116345612_33032\n466bddd49a8be3ba90fc1046ee4b93f7-1076982504506_1462125960424_51231\n2d20bd5118820a9bf668b7c0c69b32e1-10769813923902_1462090337149_5051\n2d20bd5118820a9bf668b7c0c69b32e1-10769813923902_1462090337149_5051\nc76abba9a952dc83690dfb200834b66b-10769812113194_1462124695229_48340\n936a2be0deedf765af9b47386a719f02-10769813923902_1462093037909_7328\nnull\nccd00cc8d1feb66650c00ae4d41ee732-1076982041554_1462128045040_55812\na1d212e4cdaebb58c8e583b946d1e389-1076982525550_1462089575264_4628\n9c197335d2f522506e07b388c826063b-1076984112404_1462103459423_16691\n5d3676b24a4fc54578cf2fd73b00cfb1-1076982525550_1462109946241_22710\n10dfd37534f83ac3dd94210af4c69d19-10769825327059_1462132973549_65948\n10dfd37534f83ac3dd94210af4c69d19-10769825327059_1462132973549_65948\nnull\n62da0045384b0a4e4af78617576e6f52-1076982041554_1462114194959_27998\ne8de19b5b1c0bdc4a0be32532f8772d0-10769825327059_1462087208499_3085\ncbaf10c66eb422219e390fe03738d67d-1076982041554_1462125789301_49909\nnull\nnull\n3ab977cff3d80a8181085f42b2a5bb7e-10769825327059_1462127189052_54583\nnull\n1de7623f6d1fce03ddfa9313974e682a-1076982041554_1462130893015_62830\nec8957b4bcc4bafd5b23d4eaac21cfc0-10769825327059_1462131924306_64025\nec8957b4bcc4bafd5b23d4eaac21cfc0-10769825327059_1462131924306_64025\nb76122c983bab7fd85e4f00dc2ac0066-1076982525550_1462140811706_79394\nb76122c983bab7fd85e4f00dc2ac0066-1076982525550_1462140811706_79394\na8404ee491916ee854f5f8f70c94e8be-1076982514043_1462097185598_11399\n46874efc7722619f5923fb622976a812-1076984112404_1462108442787_21238\n46874efc7722619f5923fb622976a812-1076984112404_1462108442787_21238\nnull\n65c146991b121bc1204b6dce85c8a60c-1076982525550_1462122659437_44294\n6e8af5788eb401295324082ae0fa4cb1-1076982504506_1462107453150_20525\nnull\n0decd86e79aa32d15b6ce856fde039fb-1076984112404_1462102415768_15815\nde302b8665115035f6d8b866c9572931-1076982514043_1462132831111_65536\nebfc30ed2f43c8cd1dfaafebe4198da2-1076984112404_1462120463700_40347\n1280a5919abae8b5b47bbe23684e2324-10769812113194_1462107743098_20633\n9e58040147fe1ce315a15f06a350c851-1076982504506_1462109226403_22197\nnull\n9c197335d2f522506e07b388c826063b-10769812113194_1462090025958_4903\nnull\nf260ce51844626b7c38d588b072e3bf6-1076982514043_1462089700416_4725\n972288708dd0a38ccab457333293b248-1076982041554_1462091487209_5989\n9ce29da484c48bd3105b1dee849422d2-10769825327059_1462124444437_47962\nnull\na5b8976726d7458abd2f58e18967a331-10769812118365_1462063367823_89870\n93e281e8686ee3c3a47a07701d5dc788-10769812118365_1462078148924_92485\nbdeb1c77893d8893622a897e57a66f0c-1076982041554_1462132733152_65277\nnull\nnull\nnull\ne39a9c7f28ebb174858857531da1f595-1076982504506_1462097215639_11518\nnull\nnull\n186cfbcdf13b371f26915e93dbd09b6d-10769813923902_1462135240967_71126\nba06ea78b338a8ffd20b757d00a7eab2-10769825327059_1462126012783_51243\nnull\nnull\na58126ea455f7d32c58e28a839590a6d-1076982514043_1462093369343_7823\ne450b1d4d6a3c4531979878d838419fc-10769812113194_1462115122565_29309\nnull\n05e096605f47d5d33d9fe364290cac87-1076984111443_1462060912775_89277\na09e3bf400c3633c70a3744ea9cd3df9-10769812113194_1462121963956_42052\n51798b9df22eb51cfd36e35a1358480a-10769820411854_1462078959003_92700\nnull\nnull\nnull\nnull\nb5a253416444fcc2d8e2b3aab48dd009-1076982504506_1462130576277_62719\nnull\nnull\n6c43d420c24d68883a4ec10751d25d33-10769812113194_1462132037613_64297\nc6273805a050876fe62418d82210da43-10769812113194_1462124831859_48529\n0340f1627dfb2576865095c4d935617d-10769812113194_1462110259113_22898\nc20751423f686327c0d2db5c79d5894e-1076982504506_1462126789772_54395\n7e18472d27c859bb7fd8771150cbe3ad-10769812113194_1462097099344_11252\nnull\na1203ed25662811ea2a4348c65ac551e-1076982041554_1462131604477_63728\n0170fe2deaa9486ae35a8cc4e9624f96-1076982041554_1462101164651_14677\n4e3079692a81b7a3c963e2186244cb57-1076984112404_1462090012727_4781\nc5805ae5cbf95aa5e56c3f6ecef8f3ff-1076982504506_1462121902067_42197\nc7bbd005e5d98409590de4e233b68215-10769813923902_1462122719789_44342\nf1c7e38fe93d21578b2f24d4456c1dac-1076982041554_1462093372786_7659\nnull\n2382a14fc139473597877205cc48bc8b-1076982525550_1462124821824_48588\n14649119c8e9f1bf65c6174e0030c175-1076982504506_1462111375154_24071\nacfffa9c9865a8d9cb2b0dc4314f6f14-10769812113194_1462132012067_64262\nnull\n200e3b42dc3b90e19f751ab65b1557ef-1076982514043_1462097786327_11995\n716b78c64cf2ffd0af8d9c91824581d6-10769813923902_1462134572886_70304\nnull\nb4742b73326b3afea6b49687d3a24e5c-1076982504506_1462127863527_55823\n1f06545e3d47a1030fe6b3f46e38220a-1076982504506_1462097392164_11694\nnull\nnull\n2ad26f0f25a614083f5f20b13edce64f-10769825327059_1462098166083_12220\nnull\n9090f4923f3d4280ccfa67a18c7e61f6-1076982504506_1462097689601_11980\nnull\nnull\nc9a394fde046b8cf192bf22d13268af8-1076982514043_1462129446496_58481\nedf8310eaa0c6c1d3069838020d473db-1076982504506_1462136851172_74611\nb7e09a623a9b1491c7b3084c44bf36cc-1076984112404_1462099264150_13073\ne40630447a8eb614ac8b0054c7f85891-1076982525550_1462103287047_16668\ndf8acf7d2d9d61aa6d8a1541b88e6d5f-1076982041554_1462105658125_18748\n0bb9c91914ff46aef0006cbc9515daad-1076982041554_1462096974248_11018\nnull\nb2d8efed04ff861a8247edba78ef373a-1076982504506_1462110111609_22948\nb2d8efed04ff861a8247edba78ef373a-1076982504506_1462110111609_22948\n99ab7ab3879ecfa0738465c51f72c611-1076982504506_1462110640857_23371\nebd6f27d6a7f2beea3886cfe59998c2e-1076982525550_1462139012267_78165\n396ac10ad1d99bf78cf1db45d5dc6272-1076984112404_1462135161119_71054\nnull\nb8569a78a415357240905cf0f4cf2b2d-10769813923902_1462123494091_46946\nnull\nnull\n368fa6f5e03babcd1baee7c60f2f1991-10769812113194_1462093379951_7756\n3c9bac446cf5140b159f5ca3c8e96b2f-1076982514043_1462100717823_14451\n47e039fdf058c73915a686ade5a1440e-1076982525550_1462086089029_2454\n8250a10d0ad54ec8c8878aba00333c4a-1076982525550_1462125961950_51063\nnull\n3502e1a9535ca7fbc6fa24916087e5b2-1076982525550_1462091144092_5892\n3502e1a9535ca7fbc6fa24916087e5b2-1076982525550_1462091144092_5892\nnull\nnull\nnull\nnull\nnull\n40974b27abdea82e0d28102cccb0e5a3-1076982504506_1462126559402_53930\n795302c671bf9647f7bc0e645d5315a7-10769813923902_1462092871623_7182\n2f853926588ef63ebe27a9a64fb85276-1076982504506_1462119555181_39316\nnull\n06d72c54372ea991709f879de0f19681-1076982514043_1462079484535_79\n06d72c54372ea991709f879de0f19681-1076982514043_1462079484535_79\nnull\nnull\n801dfeda5a5f7866d6fc2387bed08e75-1076984112404_1462099907253_13616\ndf1b771682a9bdcfa5d95e3bd7747108-10769812113194_1462141822137_79710\n8b93466cd3b43f416057f5545748f85f-10769825326238_1462074180003_91331\n7d225a4606c48afb2325def2e7b09735-10769813923902_1462138447602_77580\n7d225a4606c48afb2325def2e7b09735-10769813923902_1462138447602_77580\nnull\nnull\nnull\n1ff6439a85f75cb8a192804114195838-10769812113194_1462127526666_55081\nfa74e9052a03897bc6cba139e5cfb9ec-10769825327059_1462085445825_2046\n120324a7700301a12c6e25efc6e831d2-10769825327059_1462112748873_26412\n413205bf3ead520594fc0a8b142b9fca-1076982504506_1462101399986_15110\n19dad2e0dd6d72b8d6f15e9d5f244cf1-10769813923902_1462090512119_5197\nnull\n06cad25524b5dcbb570fba5f98e57f2b-10769813923902_1462118439981_35303\n00f0aeb67879cbd9785f442cc549f816-10769812113194_1462125063245_48798\nd67edd4680fdc69190458c119ef15955-10769813923902_1462080936301_194\n9e42e18b774e3a73754da4c44218e2c4-1076982504506_1462137415467_77006\nnull\nnull\nnull\nd630476119c61a0cb6fad85a81b014d5-1076982041554_1462094037563_8242\n3bd4dad02c11cd197d2a46d561b7cefd-10769813923902_1462125606004_49361\nnull\n92803b364551ffc3ac9c4c3277fac633-1076982514043_1462117188231_34040\nd96dbb335122613fc930d186d551eb52-1076982504506_1462127598324_55445\na668f9ba5f7942c1c759ee248da4014b-1076982525550_1462104933397_18187\nnull\nd89ec02d8f0f573ecfe55fa51a9c6f29-10769813923902_1462125786963_49848\n3cc0a4086dde5dc85bb85356fcf07de7-1076982525550_1462107451721_20407\nf58c76f6036b09f8fb25707f4470ccbf-10769825327059_1462138787313_77764\nf58c76f6036b09f8fb25707f4470ccbf-10769825327059_1462138787313_77764\n76a38b969f20cb3f6d3c8ccd91996584-1076982525550_1462090227750_5148\n76a38b969f20cb3f6d3c8ccd91996584-1076982525550_1462090227750_5148\n76a38b969f20cb3f6d3c8ccd91996584-1076982525550_1462090227750_5148\nc63973fde96ef5d9b93087e951d8eb19-1076982504506_1462120620171_40758\nnull\nnull\n30fecfd98162eb1739a17f34066bffec-10769825327059_1462091347142_5972\n0ba787c897c960a44a5a1635030327d5-10769812113194_1462117316225_34131\nnull\nd16b51994099e5d09d889423b1c5d73b-1076984112404_1462144576206_80841\nd630476119c61a0cb6fad85a81b014d5-10769812113194_1462098265415_12387\n9880278dfdeef443cf380ce0612d6286-1076982525550_1462114981046_28981\n413205bf3ead520594fc0a8b142b9fca-10769825326238_1462071887464_91036\n588a88cc1d461b7fbbf37fe0db730c93-10769825327059_1462111348815_23735\nnull\n49d3a55affec7a1c5baea0120b4468e4-1076982041554_1462098006899_12032\n17da4e2d3393a044093a229d56655e71-1076982525550_1462136860072_74434\n774ab5aafe9ed359df44ea71ffec92ce-1076982504506_1462128538165_56732\nfd9448260742d9b140658cd3a1c7dbd7-10769813923902_1462129520746_58829\nnull\n0692430d2d34ce02be37f1b54d661924-1076984112404_1462093444789_7690\nnull\na0b02a506d00d0863a2d43573a3f39af-1076982525550_1462085940415_2353\n6bf41e12763f82cd5a1142dc6948640b-10769813923902_1462116063675_32186\n2504c51eda96c43579547bfddd10037f-10769825327059_1462121640430_41573\nnull\n304911cba6b9d457715d92607ce763a7-1076982525550_1462126718463_54110\nnull\n70738905edef0d432dce679041012432-10769812113194_1462107709136_20585\nca355d1e31083677d97374fae9b09526-1076982041554_1462098897601_12770\nnull\nnull\ne2d14bb37bd1feaa7e583caaf44f00b7-1076982525550_1462096185930_10387\nnull\na1db363d8803a027809e9711d7bc39cc-10769825326238_1462060902471_88938\n2a449bb8147128b95d2b69a4d9579da9-1076982525550_1462090272524_5188\n5718634b88600e57f6df6f06b47a4054-1076982514043_1462100459569_14238\nfbcbd91f7291782371d8b944297a140b-10769825327059_1462128822890_56755\nnull\nnull\nnull\nbbba7ff572cb26b2007755b44434c805-1076984112404_1462107515788_20359\nnull\n129fceb06e84f2339bdd61e38277160d-10769813923902_1462143665932_80489\ndd03c139c0970e0499e2ba3fc871404a-10769812118365_1462068385371_90852\nnull\na311bcb3a9810b8656858cb72f10caf3-1076982504506_1462113792852_27826\n1f51ed27e3e9c9e70d81f6e22ceb2f32-1076984112404_1462087894991_3338\nnull\ne3dd09406093e38f98a92a2c287424c0-1076982504506_1462121865838_42149\n1fcc78384c5d34de84a6807e463fd5df-10769812113194_1462104904729_18120\nnull\nnull\nc2ce39e64b3d8bdaa32c8350ecbff92f-10769813923902_1462094874762_8951\n5b8fd67269d8ff9436ea272eec4556ff-1076982514043_1462134940807_70938\nnull\nbee7fa3ecb6b120b7546f6a0f487e3c9-10769812113194_1462090034310_4909\nbcbfdb9fe840467c2d61ec118a8074cb-10769813923902_1462088469946_3705\nnull\nf7db8b6a21c2be0b004ace3abc6cb762-10769813923902_1462118412934_35250\n08f157ed46ee6ab89a0512796801ea79-1076982525550_1462105445164_18645\nnull\n65534763de48b027aca6224a1a36ba23-1076982504506_1462080502741_349\nnull\n659d77b5a46bb2795841c18dfd9e82c7-1076984112404_1462122285770_42986\nb9903e5f410cde5582c33457ee194707-1076982525550_1462090007127_4972\nnull\n215b6b9ed79a40cd425af86efb18732b-1076984112404_1462095562579_9582\nd76e758263c77fa21455a9ffcd3381e8-1076982041554_1462118222879_35135\n6101c47b377ce759af7244b59631e073-1076984112404_1462134438200_70208\nb8142c21a50c19bd60bff836cd1e55a4-1076982504506_1462090006823_5025\n1463419ee17c339fcde15084a4523926-10769825327059_1462142913762_80086\n7f7737f2f9fb4d377c2227824a01fe8d-10769813923902_1462117826671_34602\n95355399915a79a4131e4bf48f60f171-10769825327059_1462123199109_45718\n95355399915a79a4131e4bf48f60f171-10769825327059_1462123199109_45718\n95355399915a79a4131e4bf48f60f171-10769825327059_1462123199109_45718\ne7378bfce6887838733ae76635263da1-1076982514043_1462127029682_54590\nb5d690d17a6c6d0d8b7f9a58bdeafe70-1076982504506_1462113077996_27184\nnull\nnull\n4d925252f48cf73f88507d07043d32f3-1076982504506_1462086096469_2556\na26665541b9f3300d3af36dfba589d22-1076982041554_1462131836751_64041\n7f79d9b54bd67a2d4da5d05bf4f18146-1076982041554_1462084820495_1619\nc824605062afb7bd1ecf0d3700c7c769-1076984112404_1462090604636_5245\nc824605062afb7bd1ecf0d3700c7c769-1076984112404_1462090604636_5245\nc824605062afb7bd1ecf0d3700c7c769-1076984112404_1462090604636_5245\n5426464d5efc0cc80003db96973815aa-1076982514043_1462118700797_36238\nnull\n4ff6f232a81113592457f4af07880fdf-10769825327059_1462124549843_48080\n3f782f70e8b9befaed870646abcaa57f-1076982041554_1462100738255_14321\n3aa749c49f4ca7c7fb762704aace2aba-1076982504506_1462138625769_78051\n70949e3f74e642d8260986ac0567d394-1076982514043_1462110165561_22868\n118b5b596c05718eb0a9661a8529b32d-10769812113194_1462122181271_42678\n118b5b596c05718eb0a9661a8529b32d-10769812113194_1462122181271_42678\nnull\n694da1a14e588d780aa3154c6269476b-1076981397106_1462079071025_92724\nnull\nnull\nnull\nnull\nf94e70a641add70a12c57c57a02777f6-1076982525550_1462108428437_21335\nf4f3ff92cd960f9efdd8272673ac8b2e-1076984112404_1462104424968_17628\nbc9ef4bcd26718d3d3cfdd4884d512e9-1076982504506_1462099426578_13467\nbc9ef4bcd26718d3d3cfdd4884d512e9-1076982504506_1462099426578_13467\n8e7c15f37521c432b7c226aa0cd55e38-1076984112404_1462097050787_11107\n4dc503da5238f91ced7f77bf59f92a61-1076982514043_1462111719718_24537\n1c393c9804fd8ada93ed8050c195d4aa-1076982514043_1462101389733_15019\n96b0ca43b47bcf6beb3cd7719ad88115-10769812113194_1462134319395_70098\nd65cd120fe12c7411cc99e936f434c3d-1076984112404_1462137627059_76935\nnull\n8cdf0c5adf6a5f69c3d3f82a86294e3f-1076984112404_1462107704557_20519\nnull\n066c6c36fed2faf38a8fb5063e09d881-1076982514043_1462138069358_77453\nnull\nnull\n8cdbb5a7111910c09c2bbd2e582fd033-10769813923902_1462107782289_20527\n7762d036250120be58fc009d286045dc-1076982525550_1462142518120_80120\n72edcacb5c2545304f4237f567b95362-1076982504506_1462093555690_8049\n62e1119e9f7956b41326e99bd3f569f2-1076982525550_1462139195984_78316\n040e5e44a6803973c56de89baccd4052-1076981397106_1462070917617_91326\n85d16a679bc1f272429ea57a27d76304-1076982041554_1462111370081_23860\nnull\nnull\nac76bcabf79d21841ede34c9aeb59fc1-1076982514043_1462106472650_19637\ndbeef3e30b3c49a8c302a749cd1df9a0-1076984112404_1462125959955_50982\n6e1f68829191f2e812885da1b449ffa0-10769813923902_1462107077420_19913\nnull\nnull\n349e01eb4e28a13476e483e6dbebaa16-1076982514043_1462128832479_56970\nnull\nnull\nnull\n97bd6eebb66b293b3129c77d0b842d8e-10769825327059_1462125724250_49655\n086b9f57f99f3208717f93852b511a48-10769825326238_1462078052727_92149\nnull\n0120a2616c3350991e578d0954065049-10769813923902_1462116821669_33441\n1b03a97ff55d63c7b3bc2c0d0a6e95a0-1076982041554_1462130038708_61677\n4bcc474dcdec1cf2587197e5d72b0df1-10769825327059_1462107850098_20662\nbf3b16d30e8ffb5858da90ac96652157-10769813923902_1462107800992_20549\nae9c56b4fc394a2a6c0cf54cd3ea8474-1076982525550_1462135180996_71172\nb0a64d57ae8ba6afffcd56b92f0a1eaa-10769825327059_1462096398377_10491\nnull\n610d4c7c320fae7e3ad4bc6786e8b9fb-10769813923902_1462098857587_12680\n800bddf77f86b96022b51c6c936e0c12-1076984112404_1462139473263_78417\nnull\n0d7384989f3fab012be2aaefb9fdcb59-10769813923902_1462113967664_27695\nnull\nnull\nba06ea78b338a8ffd20b757d00a7eab2-1076982041554_1462133388616_68909\nnull\n257eed66c7e81798cff273469d2f3732-10769812113194_1462130381497_62147\nnull\n73cd3a644825dcab9195d2eccc506565-1076982504506_1462140250332_79233\nnull\n51fc5da05e15c4c1c0327690c66381ba-1076982525550_1462096445971_10632\n7d7d22928d914468512e6e9001837f82-1076982041554_1462115861460_31805\nfe6704c8175faf565a5a10c12ff8bc3d-1076982525550_1462131469576_63628\nfe6704c8175faf565a5a10c12ff8bc3d-1076982525550_1462131469576_63628\n86901c26598da1c7dc027b6997cc1b2c-1076982514043_1462131480730_63678\n0d44548a3b99a1a891540a687467209e-1076982514043_1462102640412_16131\nnull\n0d44548a3b99a1a891540a687467209e-1076984112404_1462103110427_16384\n3061a4fd1d6393707d68f7d587a3d45b-10769825327059_1462106447407_19458\n937a1c0ac6f02e0c7992f586fcfb4b53-1076982041554_1462091842651_6261\nnull\n2a8ac3f4a4e22f5f7b849cb4c48deea2-1076982041554_1462093352827_7638\nnull\nnull\n1bc0384d8273afe08012a98d105f81da-1076984112404_1462111621438_24216\nf9f6c1bd491c38e668d958b19e2ead31-10769812113194_1462109194923_22017\nf9f6c1bd491c38e668d958b19e2ead31-10769812113194_1462109194923_22017\n9ec24a3cd480dc51bac3f44bc94dde1c-10769813923902_1462083902337_1154\nnull\n348e28714d5dc41c723144ca6e33aa8e-1076982514043_1462120677177_40710\n51e3f563def781c98890531494b54826-10769825327059_1462115170602_29361\nnull\n3ba895801dbf2dcd4cc510711922215e-1076984112404_1462095843566_9855\n386939ec1f22de744f22f34ce7537532-1076982525550_1462102665069_16155\nc194f9588cb472a99e8e3318982e556e-10769813923902_1462135190709_71053\n99fab79286f51dcfffb5c54daf1b750d-10769825327059_1462127123026_54501\nnull\nnull\nnull\nnull\nnull\n99467f70eeee8a1d42b954bee01c2a2f-10769812113194_1462101794419_15323\n9894e68927f07a42c2bb7ab630675856-10769812113194_1462084454669_1505\n7e79e9816a1b32b41ce37a54e90d2760-1076982525550_1462104381939_17687\n07dc6029b1a5678a19e3614af262bade-1076982504506_1462124582887_48439\n3a29401ec8d9d79e8a2c9b9eb675a413-1076984112404_1462112039332_25018\nf3a2d38c51f5404b40a68bdab4e5f9eb-1076982041554_1462130563863_62401\n331e4b355e6ab970af300a4444d11267-10769812113194_1462136183434_72116\n445b7442f791272b480a4a8c9a9591a7-1076982504506_1462105331051_18671\nnull\nnull\nnull\nnull\nb13d6930d802a2d58a36fa5c6eba5eae-10769812113194_1462127004570_54407\ndc2f38b5da594542ef816a2cfa35b9b4-10769825227166_1462071659151_91534\na0aec9322a6392c7bec52f73ec03570e-1076982041554_1462107671941_20504\nnull\nnull\nnull\nnull\n03f14b14c92ba4e02d16706597db124f-10769825327059_1462115030099_28938\n14b13f228a26e5904fb941a08b1a5bfd-1076984112404_1462112800402_26552\n14b13f228a26e5904fb941a08b1a5bfd-1076984112404_1462112800402_26552\n54602073f3e97703f12df3fe42c488de-1076982514043_1462111372944_23938\nnull\n590e6a210d1e040cccb065841994118a-1076982041554_1462124779248_48465\nnull\nnull\nnull\nde860257ca3b96109888a4088226371e-1076982041554_1462134832983_70645\nnull\n4dcba34d28a3ca14c2e70cdb2ad9aa59-1076982504506_1462104386394_17796\nnull\nnull\n9cb45ce481ba9350f56da260bbc8c28c-1076982514043_1462092502509_7010\nnull\n862c04b2aba243768509e60aa42c9fbe-1076982525550_1462131889102_64189\n2ed064852c5f37d2c677a7a2b3642eb2-1076982525550_1462090009626_4976\nba8d827dd79cbc119f539a8b98b96c4e-1076982525550_1462133450818_69144\nnull\nnull\nnull\n3ef2e433f9810186f3baccf49e5d2487-10769813923902_1462123024499_45233\nb823010a5d464e32661830d9f62fc359-10769812113194_1462120136486_40056\nf7739d7858000b5fbfbf441e64c6e5f7-1076982504506_1462131728082_64161\nnull\nedbcd8f2daf67054bd755813acf6b8d3-10769812118365_1462071631664_91318\nnull\nnull\nnull\nnull\nnull\ne2c072e2b5c0a6e5bfbf61182012c9a0-10769812113194_1462127960378_55691\n0dea993bce2aa2d51f91f45bfc642115-1076982525550_1462087882009_3542\neb108ebaea188d515a4227129dfe2f9a-1076984112404_1462135277467_71205\n0dbc9d331819efe1336514f6c66899f4-1076984111443_1462071695475_91335\nc469a23e783c97fdb72310feee19afdc-10769825327059_1462107782168_20572\n826ed080926d70b97c7e511726587e6a-10769812113194_1462080976911_290\na16760186abbe4dbbeaa2b0afd79f040-1076982514043_1462100616021_14364\nnull\nnull\nnull\nnull\nfe03c425ee1fe1731b4102a013fd0a1b-1076982041554_1462119841948_39753\nnull\n074173e44c23f102fc50f9218b45abc4-1076982041554_1462090022980_4830\nc6a16598cbec75545fcd190436c0892b-1076982514043_1462143698746_80636\n1d05573275a5231c6630edb8a21a0bdb-10769812113194_1462100864478_14529\nnull\n2249eabdd591cdf6d3f1d9fbddfdd10b-10769825327059_1462109834613_22450\nefd1c3eef9ab3ba6a73519d0723c4db2-10769825227166_1462079117761_92857\n8346362bfbcae18cdd5035a6a793a88f-10769813923902_1462133892951_69575\n8346362bfbcae18cdd5035a6a793a88f-10769813923902_1462133892951_69575\nnull\nnull\nnull\nnull\n93e281e8686ee3c3a47a07701d5dc788-1076982504506_1462097663148_11956\nbab2b39008ff64ac80b8cc12a09a0c6b-10769812113194_1462108751770_21625\nd2c488cad3786156001d4bdad8ae414f-1076982525550_1462095606383_9802\n074e933b6ea10cec76d445f008e1976a-1076982504506_1462097392164_11694\n074e933b6ea10cec76d445f008e1976a-1076982504506_1462097392164_11694\n91db484eda9b33c2d92198ce0bc7d299-10769813923902_1462135667588_71565\nnull\nnull\ndcecf53f5e6ac4fc2a73eeeaf109c362-10769825327059_1462128570908_56444\nfa4d5ef8987ac397dcc9e91a5d92a02c-10769813923902_1462100866121_14372\nnull\nnull\nnull\n818c6f8109d480a5af7b61efb4bb15a0-10769813923902_1462089746962_4570\nacb7eabc67337010eef49bdd87ed9b82-1076982504506_1462097392164_11694\nf297ac0d300a9b9c14c54a36121eeaf1-10769825327059_1462093936301_8217\n0e285b2030bd4fffd012bc6d85063bee-1076984112404_1462096356662_10400\n0e285b2030bd4fffd012bc6d85063bee-1076984112404_1462096356662_10400\n4f81d37a458d675b7aa9240c55d2329a-10769825327059_1462127581844_55108\nfe0e346dead60a7a7271708dd53baa81-1076982514043_1462119121770_37631\n064a2d5ca0c12b4cdff8b8be6efdad1e-1076982514043_1462126065062_51646\na311bcb3a9810b8656858cb72f10caf3-10769825327059_1462118266005_35102\nnull\nnull\nnull\nnull\nnull\n7edb68d347c2a06daa4304eca73602c1-1076982525550_1462085845324_2295\n1129d3f09b6e0048bae1ae392083f7bb-1076984112404_1462120074213_39961\n73577d81e9c4b38dba716b9b873db846-1076982041554_1462130971787_62930\nd74a6133d14966c745c3ac016c1c8d67-1076984112404_1462132659313_65161\nnull\n6f18b0ef1c30b498f1b5ae20b008ef38-10769825111603_1462066523038_90885\nd9594eda16a5e2ec1e34b424afd2703e-1076982504506_1462093735985_8214\n13b873553e617daea1a5f66693bcdff1-1076984112404_1462127098113_54536\nnull\nnull\n90cecb44a6ec54bbe1a50687a4f37daa-1076982525550_1462121119471_41120\nnull\n0f330891e1185524105fc02469a49430-10769812113194_1462093364774_7738\na2916588a2b9d41c9c055fa6e05e4cef-1076982041554_1462084647977_1531\nnull\ne2ebed9bacb56b8ffefb2697613f8cdd-1076984112404_1462112580868_26084\n8c798599fac575f4c0132b13d4317088-1076984112404_1462099575362_13351\n33ebf2025d345320681cacbc923e9c55-1076982504506_1462095685630_9967\nnull\n0bd7685e0a3208a4456e924e93a8cf73-1076982514043_1462143947809_80728\n68c39cb7b12466989e23d1bdff9df43b-10769813923902_1462086128468_2322\n4c781bf1b0aad3b4475139c3a4c4775f-10769825327059_1462131361772_63299\nfc674c68722305d350ad74050ac81d00-1076982041554_1462136692395_73491\n91c8e8624fefd37eb6d65ae2d9f84df9-10769813923902_1462089960047_4745\n4e78b4002d887d90b0081e27ac2767a5-1076982525550_1462114915905_28868\nb68f5731760394492bb9d6884230562e-10769825327059_1462088627039_3945\nnull\nnull\n1b23f4382d12aa56c387d1840d452d98-10769812113194_1462121376642_41352\nc51ac3bf89beb1a1d7481e77fcff1934-10769813923902_1462100129340_13737\nnull\n42293afc211da8fcc2929b23c334ec9c-1076982525550_1462111358629_23909\ne75ba239554b99fda7f5ac38d402f1be-10769825327059_1462141402665_79497\n2b6cab6213766b399b3a96b67afa0a29-10769812113194_1462118419613_35360\nnull\n108a0cfab81386ec6bb994ca5acee196-1076982514043_1462094038865_8405\nbb27ed95fc23da886bc8c2578b8370a5-1076982525550_1462130417118_62283\ne5d4cf0905ca6954c09a7fec99fcf169-1076982041554_1462082401236_610\nea0ee99b374f9ee1b0a82ba3d36378e3-1076982514043_1462116027858_32267\n1c390dd3ce9a85bcf20eefd2cf561795-10769813923902_1462131276029_63267\nb1279934823c4b6dfbff7b3a60e30995-1076982525550_1462100620195_14353\nnull\n07b69e50d39fddf564ef766e3ad54955-1076982041554_1462099398253_13210\nf51d5f6d7343fc4b28577fa633d98e84-1076984112404_1462135044505_70919\n473e4c68540e7d119a2394a3b0796121-10769825327059_1462107777355_20563\nnull\nnull\n4912113edbb4434faf00b89b882e1758-10769812118365_1462063367823_89870\nnull\nnull\nnull\n67f678e7c6da1fb02eaf5c3c7b5e359a-10769813923902_1462086102379_2303\n289fa98d316b8f2d2383eada93ef67d5-1076982041554_1462128103751_55886\n3713d368348cffd44b134a7340e747b4-10769813923902_1462134656346_70397\nbca5c342b5ac655494b557e9da545480-10769812113194_1462112800433_26613\n0fac063d00e7e65cccf71d019919eeb0-1076982041554_1462100413259_14050\nb90b07a8f83a075e05e2037919b77e5f-1076982041554_1462096400046_10421\nnull\nnull\nnull\ndf720ad63e53c268d5f55ea419b1249d-1076982514043_1462119276950_38223\n01ced69f3238f5adafb49cdf31cab668-1076982525550_1462123772065_47386\n01ced69f3238f5adafb49cdf31cab668-1076982525550_1462123772065_47386\nnull\n34ea0742cec37ae9ea70e1965592f178-1076982514043_1462112279872_25520\n6f7d88b6cf563f856eb22603ed6c8e6a-1076982041554_1462101007703_14542\n0283095be13f656217870f392570b3b9-1076982041554_1462113841278_27678\nbc5b1b36c1fcc133252d25619e58ab99-10769812113194_1462093943130_8250\n167c6700b236f3355c53a0a1115ae9ee-10769820411854_1462071062274_91313\n7065ab876ba455bd8f8dbbb16703f3ed-10769825327059_1462100767928_14351\n741cd0fadbace7507f26ed9e998b778a-10769812113194_1462116301068_32957\nnull\n74c9fdb2fd51b73d644f981f0dcca8a7-1076981397106_1462071690027_91429\nb31654dbeae1bd8c364918f91ce2a69b-10769825327059_1462084623436_1619\nnull\nnull\nbab812421d392b07d898520f73bbadd0-1076982041554_1462138664619_77749\n7410646ab24ed45106d772e57a556b50-1076982514043_1462126081275_51711\n7ae651c2c901a3b68b46a91327b7ffe6-1076982041554_1462129023195_57078\n2123f73612ae518871f59dd33be85a79-1076982504506_1462130093765_62049\nf01a84eaf505e21e08601e243e467665-1076982514043_1462118134947_35117\neec801fb8f47e6a4d268462dd7766e7b-10769820411854_1462070033470_91183\nda82b7bf8de314ad6d5346ecf52a21d2-1076982514043_1462086130713_2494\nnull\nnull\n87017b6accb82db55ee166d14bfb6ad0-1076982504506_1462133322750_68943\nnull\nnull\nfa8092e288b6e676bad8ae2c1bb06589-10769812118365_1462078915871_92634\nnull\n758763cbe42e04f1e7ce1157ca96b9af-10769825327059_1462111624972_24183\n6a4c6387abcf8930827e95e3c028d689-10769812113194_1462100742782_14410\na3bcddd2c1f915a4764302dd3734aa09-1076984112404_1462123851171_47402\ne8de19b5b1c0bdc4a0be32532f8772d0-1076984112404_1462096045916_10065\n8495ece822ab35925a2a3fdc502912cc-1076982504506_1462113243405_27336\n124316355b5ee34d17d21ff97ef17f74-1076982041554_1462096441375_10458\nnull\n3f66886ad877c8a2c960f7c7990705b4-10769825327059_1462102735184_16053\nf7db8b6a21c2be0b004ace3abc6cb762-10769813923902_1462141668872_79656\ne29c823c0c162933739388c8e4901468-1076982514043_1462097209409_11428\nf906065e53eb4660d79e49dd8462d9ad-1076982514043_1462140141021_78998\nnull\ncf41fef2559c3e97269f005c3f0caca3-1076982041554_1462112133011_25209\nc1b204e5fb061b3132907a126179654e-1076982041554_1462095592629_9637\n2099b14c345691e393c1a25c5dbeae54-1076982504506_1462137274130_76512\nf3a2d38c51f5404b40a68bdab4e5f9eb-1076982525550_1462121089641_41088\nnull\n204dbf19e7592fa5bfc852fd5030f024-10769812113194_1462089997578_4869\n31259afd3542ecc5d70a68504a4a7965-1076982041554_1462127145832_54589\n936e5c6751cecba47f5b483b3febb8ca-1076984112404_1462083220819_851\nnull\nnull\n3fbacf3e8f206c07eece7e3cb59a46a6-1076982514043_1462101777313_15352\nnull\n89321a7236a97af817ef82b70a452ca2-10769825111603_1462078912786_93015\n69a39693048fccac36f206abad898485-10769825327059_1462140262163_78844\nnull\nnull\nnull\nnull\n4906d7ae2f3b18b7373d895343f46baa-1076984112404_1462084247421_1270\n282053d62919af5771cbe4c7e5360dd3-10769812113194_1462090839544_5552\nfc1f445a7733aab1669161e317e838a4-10769812113194_1462100235021_13998\na5ea7ced473854721e69b0fe8621dfa4-1076982504506_1462098164304_12438\nba7a4d349dc57d693bee12deea691df1-1076982525550_1462122864002_44839\nnull\nnull\nnull\nnull\nnull\nnull\nf90395f3753f2af0d681e7aa3e4ea5e5-1076982525550_1462100469019_14224\n139d47a51cbe1a47c9dd1bd3b1cbba19-1076984112404_1462100851975_14428\n2a0152f7fb904dfc763460c273e58aaf-1076982504506_1462097392164_11694\n2a0152f7fb904dfc763460c273e58aaf-1076982504506_1462097392164_11694\n051a94fcfeef49c1315a8216619698b0-1076984112404_1462134199756_69967\nnull\ncd192ac95e0b0fd05990665ddb875ee1-1076982514043_1462130588344_62563\n329032efe60ebe43aaeaa023846fc4d2-1076982041554_1462115942843_31996\n329032efe60ebe43aaeaa023846fc4d2-1076982041554_1462115942843_31996\nnull\nnull\n28c98caa50df041a67394f2e7812b8c5-10769825327059_1462095049019_9184\nda29762616c23e037e36061271c09fc4-1076982514043_1462090936760_5724\nnull\nnull\nnull\nnull\nnull\nnull\nnull\nnull\nnull\nnull\nnull\nnull\nnull\ncd52eb24da705216dba3e215dd50413e-1076982041554_1462105618421_18715\n2db1608d77e0227cebdcb18a0d626058-1076982504506_1462119504636_39164\n413205bf3ead520594fc0a8b142b9fca-10769825227166_1462078958054_92826\nnull\nnull\nnull\n4af9af3629d68e1a355d73bfd5bf4c57-10769813923902_1462132314183_64644\ncf5a24a7129cb8808340b905bb7a22a7-10769825327059_1462133956932_69566\n4e3e3633bc2bfa51b69d6b1e246ed34e-1076982041554_1462104349930_17546\n10283f91acc07b148fb621b05e86e36d-1076982504506_1462095845176_10123\nnull\nd8e5d11d41052790b3a5e6e6da880ee6-1076982041554_1462094630978_8756\nnull\nbf59365886a375870222d7d84450331f-1076982525550_1462120532486_40495\nnull\nnull\n8d8c6af1ff9a8b96f34e5997dd18623e-1076982504506_1462107665924_20702\nae9c56b4fc394a2a6c0cf54cd3ea8474-1076982504506_1462139037038_78389\ne860c1f8e9658141b09ae699a4010437-10769813923902_1462107711020_20430\n18e0cb9244b37e2ba13fa1706f87234e-10769825327059_1462096398377_10491\nnull\n00de169eb92fe9a22baeced573c628b7-1076984112404_1462123753665_47282\n7315e1e9bd6bd96c1d38988582e67c3c-10769813923902_1462110960152_23330\n7315e1e9bd6bd96c1d38988582e67c3c-10769813923902_1462110960152_23330\n1390e4280db151fcc679b0fed7ccf054-1076982041554_1462095476703_9515\n383f90cfe6e0f0bc2362c18fe44ccd13-10769812113194_1462113388586_27286\n4b99d08611cd518950243894d9ec635f-10769813923902_1462093880972_8103\na01e72294b306c3e67febfc8d79fe75a-10769812113194_1462135534775_71477\n9a432cfcb8f7ceb75a0068b5198f1e93-1076982504506_1462087666753_3483\n4e87119439e4d7d262fb98370c010eb7-1076982041554_1462139220634_78194\n4e87119439e4d7d262fb98370c010eb7-1076982041554_1462139220634_78194\n0a7c8acf904040dc95ce3120d4d901d3-1076982525550_1462116486413_33204\naaafd17a4eac221e183929bdf449cad8-1076982514043_1462127841799_55677\n6a55fd92ce4c9e4174c8162e28c1b773-1076982041554_1462113275531_27169\nb52b4a96b9384f7837e81b9d902fd045-10769812113194_1462126205512_52014\nnull\n705e42914a1711695be662e19e5ae3e4-10769825327059_1462123885065_47378\nnull\nf1fd53b557d7e34662b10cb238906c0a-1076982514043_1462100672177_14411\n56210e2cc7f184ae704c7072c16fcdf7-10769812113194_1462114724369_28559\nnull\n6e157ce666c9f1b6959a64f949434262-1076984112404_1462114204196_27964\nnull\nb7f43c1c25371abd8a78f5f5f7b7a1de-1076982041554_1462111583704_24165\nnull\nnull\n0a12d7f930838e82cd80778334ceaf97-1076982504506_1462085123323_2038\nnull\nnull\nc29c5c4bcf9b4776eaf6b1d06fbcfbc0-1076984112404_1462092327554_6655\nnull\n1f6713dce24e151b5acd6a4ce917e177-10769812113194_1462130543080_62365\nced04936bc42806ae23d8920ada2b5d4-1076982514043_1462105203319_18452\n5d6eda5b81b1102e8285d5619be7b4b3-1076982525550_1462093281377_7710\n2f3438f4cba234b8c0d5623966098f57-1076982041554_1462102511065_15897\nnull\nc3123c13a829b288bdb63b983723fe15-10769820411854_1462064516113_90305\nnull\nd39f68ad2ce30dbb83e0fec68bdfb2fa-10769825327059_1462097197914_11280\n64383e87c46c3cc7c0b21933b2aa12c0-1076982504506_1462121598395_41820\nfba48bdd95caac9a52cabf88412124aa-1076984112404_1462100021668_13707\nnull\n0c75686cb91ea2425ed10432f9478b28-1076982525550_1462112533638_26063\n36d87eb94fa6d256caf27746f5cdf030-1076982041554_1462128861172_56873\nnull\n08b458dde3ed54c65660f39741cf5e39-10769825327059_1462087171124_3060\nd1bd0e8d7f35be1dd38cbb7830428f52-10769812113194_1462118801404_36444\n155607270a579ebb013879201896d548-10769825327059_1462088262318_3715\nnull\nnull\ne271a1bb32f9db0d911824d87bc0ac06-1076984112404_1462085316227_1831\n284c561b21b2f744d5a0135403137c2b-10769812113194_1462127696763_55317\n4632255aef82f9811245f650f2af27d6-10769813923902_1462097944105_11940\nnull\n145c0be547a94469e23db19d22cbea77-10769825327059_1462105660500_18701\n3d0dbb64f56f269a4d8396384c90873f-10769813923902_1462133520566_69133\nnull\nnull\nnull\nbb65dadc5262110fd821b94d9396865d-10769813923902_1462111361479_23729\nnull\nnull\nnull\n8ad6191c8555eee0faeec36caa8f1674-1076984112404_1462096690411_10724\nnull\n74f46984846ec7eec470cda857aac2e6-1076982504506_1462117742468_34818\nc768199065468a68c53c7e7c85c7cc52-10769825327059_1462138740026_77735\n783d56b912e146ce0c3b359bc337e95b-1076982525550_1462101775435_15340\n783d56b912e146ce0c3b359bc337e95b-1076982525550_1462101775435_15340\nb264a50d1d018c2539b64a679b9eb60d-1076984112404_1462107338974_20215\nnull\n2123f73612ae518871f59dd33be85a79-1076982504506_1462131932122_64454\n4a1b7f4435cb08dbc63d96edd7e98eaa-1076982525550_1462111359424_23912\n04e8eb446801a081ef5e8f4dba1f8582-10769812113194_1462090406075_5206\nda8a0107b26a64a7ea3efca16261b5bc-10769825327059_1462123824919_47307\n413205bf3ead520594fc0a8b142b9fca-1076982041554_1462101500425_14975\nnull\ne353626e31b94f8bcffecc25ccf1a999-1076982041554_1462130308031_62067\nnull\nnull\n5b78decc15e899f7e8bd3d943b4684a1-10769825327059_1462126958511_54288\n0c5aa42e2d3bb01affaaf10fe0b5ddc2-10769812113194_1462117786880_34665\nnull\nnull\nnull\nnull\nnull\nnull\nnull\nab96f3db33431a0a7c3c2640bfb2f15a-10769813923902_1462107818958_20569\ndc576413c90f7eda9e48928a2ba4bd7a-10769812113194_1462092525226_6958\nbdc8aa301e98347b50277ff8dae93950-1076982525550_1462090308924_5219\ne4a34821a005117686aef3a821b66222-1076982525550_1462107869393_20814\nnull\n0c269cd7f9b40f0cddcd48a4a849bd87-10769812113194_1462094437212_8676\n635580e2be08cf180efcbb0e884fd2eb-10769812113194_1462089528226_4502\nnull\n1e57c133e3bd854b62e444ef034dfff8-1076982514043_1462090007086_4978\nnull\nbb16a73048d1a022d45a354b31b2cf86-1076982504506_1462091418649_6169\n94d9f14d8db8bf1287ff3684c1b34df6-10769825327059_1462115049005_28970\nnull\n750ca2a267d294d6a88c7886de071bca-1076982525550_1462101516082_15122\nnull\n647b7f467cf6e7a266dae75a5cbc6e9b-1076984112404_1462135930739_71904\nnull\nc8f7b1e53010425f08f209c969de20b5-1076982504506_1462134290219_70375\nnull\n88f10e908d274e89eb234730dc26c8ae-1076982506413_1462065187427_90595\nd355eeabc0f736ac42d92c768085c483-1076982504506_1462107300196_20406\ne5f3b4a0d0a818a7e2bf9a43774cd58f-1076982041554_1462100465571_14092\nnull\n6b79a6a9218e2c0c7d8eb838fdc0680b-10769812113194_1462125038812_48773\na42a11d2aeb00e0775a623c1c5c5275b-10769813923902_1462125892324_50281\nnull\nnull\nnull\ndbca2e0713cd6584f2f26a4a2ad74652-1076982514043_1462097102777_11320\nnull\n8e23b1680a5b30b9c94502bc4e23d1a7-10769812113194_1462104958498_18165\nd16b51994099e5d09d889423b1c5d73b-1076984112404_1462122241640_42858\nnull\n6e97bc346824266b74e917f8d43c4911-1076982514043_1462089760637_4776\nnull\nnull\n2368e2028c1d6d2b5da1117692fbc24a-10769812113194_1462102640484_16088\nbddfbd90552887ba6df8b943e363f247-1076982525550_1462145666836_81213\nnull\n1c393c9804fd8ada93ed8050c195d4aa-1076982525550_1462131160040_63252\nnull\nfa1e57ca0630cb380b7e4e4829019140-1076982041554_1462145605971_81046\n68dc6dc2df3a0e81e6cf283387e6107f-10769812118365_1462060843199_89263\n2a756daebd277b62ee0ae45d2cfcbcc2-1076982514043_1462105733370_18939\n953b31717860fefafca7b1c6342f6592-10769825327059_1462104216716_17371\n6816434391ea0a7ba8fde4fca05f749a-1076982525550_1462096105787_10302\n80eb928f549672f5cc04c4d00ee91bee-10769825327059_1462091638827_6196\nnull\n16401c69c57a9c1d765e8ada182c54e7-1076982514043_1462128293877_56297\nnull\nf5acdfa45c186e7bc7b16cfd5d71c5f8-1076984112404_1462116003130_32085\nnull\nnull\nd96dbb335122613fc930d186d551eb52-10769813923902_1462138961644_77990\nnull\nbdb462f8531bf705c033a2f62511a13a-1076982506413_1462065131042_90585\nbdb462f8531bf705c033a2f62511a13a-1076982506413_1462065131042_90585\nc29dedda4c7ffafab14ec85387a0b1b8-1076982504506_1462140329057_79265\ne7fdf81550b1d592e3ae40631701a90a-10769825326238_1462068186472_90512\nnull\nbcbd436269d8f6a4ad2869bbea43a767-1076984112404_1462110326610_22884\n01eef17f8ff030cf86cd161fe053bf09-1076982525550_1462100819826_14522\n8cdbb5a7111910c09c2bbd2e582fd033-10769813923902_1462104391740_17500\nnull\nnull\nnull\nnull\n779ddc265c295f1b2d56013471aabec6-1076984112404_1462127527426_55088\n19ecc33e4c086a3fe36cdce89f65ba80-1076982525550_1462100852874_14558\nnull\n72b3f3544e98088e5bd5cd8fb9f730c3-10769812113194_1462108070435_20999\n07ba2d3cee336a71aab1b793fb81eb33-1076982525550_1462111381804_23949\n125d821ee2cfa3a56386dcdfd3d7ac87-1076982525550_1462088962818_4230\nnull\nnull\nnull\nnull\n96b8ead8c3e4ab8c68962aee156319af-1076984112404_1462090479550_5156\na803d4fc0cacd588ce43a1808222c650-1076982525550_1462121702099_41765\n23763152909a88a9565ed16d750cf328-1076982525550_1462125840777_50164\nnull\nnull\n479309342806d536b0e62138ad0fb9c9-1076984112404_1462113441568_27265\n8eb155bacb56d0131ee704634d16e66c-1076982041554_1462100613582_14215\n6c825e99a534fdee7b12183003343a3a-1076984112404_1462116800483_33468\ndf11e998d84a66d91229306e394e9a5f-1076982504506_1462097392164_11694\nd0f11793df9ec29239f54e3b3087980d-1076982504506_1462082835483_978\nnull\nnull\n262f2b1d63dab6c65b13d1cb3c3af458-1076982525550_1462111471457_24078\nnull\nnull\nbdb462f8531bf705c033a2f62511a13a-1076982525550_1462106663157_19765\nnull\nc9d76291fffe74b23132060c1386f5e8-1076982504506_1462113296245_27387\nb20ef6c52189cf74bae017ebdd59f94d-1076982041554_1462082795001_737\n0c42fc42f52537f26e345cce569da7fc-10769825111603_1462060863250_89595\nnull\nnull\nnull\n46e517358361c0db5ff345ca470a8450-1076982504506_1462093450012_7951\nnull\nnull\nnull\n005d6adf64e828162187152bde8e1cab-1076982504506_1462128352239_56505\n77b5c0372fb0d98cb0805d417d463a73-10769812113194_1462104877583_18089\n32a487ec2428f55fb32694341dae063a-10769825327059_1462113910007_27666\na26665541b9f3300d3af36dfba589d22-1076982525550_1462105489938_18692\ne653f83dfdb9223ea8cf1a8a7cd813fd-1076984112404_1462096443843_10482\ne08c46142938f7834bd3632ffac7b8c7-10769812113194_1462117577911_34428\nnull\nnull\n69d66f25945a5f7ed56c44a8d2a0258c-10769812113194_1462121498031_41486\n96480b0a1ca26cdcebf1ec040daee004-1076982041554_1462080845419_203\n797f0a00535398ddbf3220a2b74fd76b-1076982041554_1462107795682_20648\nf9dcffc7846dc37c1a4c42819e44b7c9-10769813923902_1462115397009_30037\n99fab79286f51dcfffb5c54daf1b750d-1076982514043_1462084600832_1667\nnull\n3ace7f9e0d8e7abe8ba24dd551971309-1076982525550_1462137315378_76514\n3ace7f9e0d8e7abe8ba24dd551971309-1076982525550_1462137315378_76514\nd3382e27d22b92f48a077561ff8b60ef-1076982525550_1462114982548_28984\nebdeae508e05c8f10f30a33b7774823e-10769813923902_1462126307500_52231\neda7cc0bfcd666e9ee60c4dbcc49b772-1076981397106_1462064191688_90252\ncce92243d7ff6283ab889fe7de9c4d46-10769812113194_1462097974242_12115\nnull\n2a333ce129be064bb9dabbece2888971-10769812113194_1462129524643_58871\nnull\n13ca8f578efc84bbb45e9fa7a0bd3a2e-1076982525550_1462114881551_28781\n\n\u003cfont color\u003dred\u003eResults are limited by 1000.\u003c/font\u003e"
      },
      "dateCreated": "Jul 3, 2016 9:38:29 PM",
      "dateStarted": "Jul 3, 2016 9:40:36 PM",
      "dateFinished": "Jul 3, 2016 9:40:37 PM",
      "status": "FINISHED",
      "progressUpdateIntervalMs": 500
    },
    {
      "text": "z.show(offerId)",
      "authenticationInfo": {},
      "dateUpdated": "Jul 3, 2016 9:40:51 PM",
      "config": {
        "colWidth": 12.0,
        "graph": {
          "mode": "table",
          "height": 300.0,
          "optionOpen": false,
          "keys": [],
          "values": [],
          "groups": [],
          "scatter": {}
        },
        "enabled": true,
        "editorMode": "ace/mode/scala"
      },
      "settings": {
        "params": {},
        "forms": {}
      },
      "jobName": "paragraph_1467574841901_-528925284",
      "id": "20160703-214041_1759231912",
      "result": {
        "code": "SUCCESS",
        "type": "TABLE",
        "msg": "substring_index(offerViewId,-,1)\n5d3676b24a4fc54578cf2fd73b00cfb1\n201c12fd658faa802f35db6da9ade2a8\n9af4a10e737255532e69bc08823cf820\nnull\nnull\nd9594eda16a5e2ec1e34b424afd2703e\nd9594eda16a5e2ec1e34b424afd2703e\nca6cac2d6b4168bb7b320dcedcfdae5d\nnull\nnull\n85d16a679bc1f272429ea57a27d76304\nnull\nnull\n3358b3f0332ad2ccf1795ab6ba1b2bad\nbc9b163edd4d5327be9d961b0b2e1986\nbc9b163edd4d5327be9d961b0b2e1986\nnull\nnull\nnull\nnull\nnull\nnull\nnull\n2beae2f482dc031732010cd1c583c86d\n11ef2eba8ba8bdad00ab87ad0d6f7109\n2fa324819ba9fdc5c28a74356799c049\n5cd850dfb0fd858d21623cbcdd0de4e5\nnull\nae3d43fc2f70c2521d544965ace6129e\nc5fbe45650e3fae7c2d60d461f80fc14\nab06a0a98c45f27ae0aee1ef792dfbe8\n595f35fe3de601a72d68b12b447e2560\nbc4c23ec458e902de84e035ec18a04be\nnull\n3032c3a83aa0f588e1c02791fa3a628b\nnull\n0cd791e39646070913b7c20899ee211b\n58488a145186eb49e0cac648651344de\nc76e2d9a61fc563747246ec7c605b27b\n7196b23750d29ef7f7378a55671fbb86\ncac10f0f471f17e66c4eb62e497fdfb1\n0c5430549bd2d7ca9f1a9ccc03ca6f17\nnull\n779ed718b1811d8ca059f33b8c0daa20\n0c06820b06e3e684771a4ee2ae47bf5b\nbdc8aa301e98347b50277ff8dae93950\n02ab810a9e666af7a58bb576346b5016\nnull\n6bcfdf04a206b3ae60c417d5d98b1b49\n6bcfdf04a206b3ae60c417d5d98b1b49\n6bcfdf04a206b3ae60c417d5d98b1b49\n600823cc1779f707dfd20c47e0eb39a1\n8eaad66df52786d6a25508fe320be7e8\n50bd10ae4625fb78e26d613138983389\nnull\nnull\nnull\nnull\nnull\nnull\nnull\nnull\n2db1608d77e0227cebdcb18a0d626058\n0db22d3180be67d3ce11f8c9f59ee073\nnull\ne6d91eaab409f4b6f06fcbf3183cd3e2\na4afda6722ccbbc584331a915454849e\nabedcc442b42bae493ae8c00cb39f20f\nnull\n08b458dde3ed54c65660f39741cf5e39\nnull\n55cd134343777481ab26deade6ea62aa\nnull\nc6ff34a6d631d637ea52458eb98e2514\nnull\nnull\n37539e831ddfdca100ad0f8d39e07276\nnull\n57231353f47b0291462de4ec6221259a\n57231353f47b0291462de4ec6221259a\nc2d8c72aa369ef0ef7d4bab511d69589\na267c0e4992d68eb7907b2000687599a\n08b458dde3ed54c65660f39741cf5e39\n754483dd310231d1c0dc86f0c807b44c\nbbe7b50850acbd73e2b10ec24ebba294\n5c9319ddb5db134ca3d3e5d17ef0e115\n9f1f66e132203ba060cf8951eef52b94\nnull\nnull\nnull\n75e29fae3fb5374c275c5998400f7b2b\nf42ebbf9a5885faaf3faca09e20daf95\n9dc3eb2c84def8fe041d93e6e3ae1a26\n7bc7a074188aaa1761af43bbdd0a0ba9\n5e0f9a31e5aa523e06f043accd795d23\nnull\nnull\nfc674c68722305d350ad74050ac81d00\nnull\n735f50f627bae1805a846379c7417a99\nnull\n63c19b5b0183f828fcd7472578b9c4c8\n5084d0f7bc1edb911d6fd86a18649ac6\n2a0b781a77ecb6441fc793e36d6bdd3e\nc13bdc5a48274bad00f6d33f598d5ccf\nnull\n2fdb297c9b11e933f5c10d59f5b84027\n2fdb297c9b11e933f5c10d59f5b84027\nadfde0c4f3d7316e177f67571f65d6c7\n6bb33f3e628e07d353fcf17c526758ca\n13492098a67300530969caf18a1852b2\nnull\nb5c9376dfb1955207918ee4cb02f171b\nnull\nnull\nnull\nnull\n0110a549147ef65a3448b2c150c29da9\ne33a2d4a0c64959dfd33177ce450dcb8\n4f065187cde3d6259bc157d1d99bdcbf\nnull\n22fac07a44fc1b5cd01ed1ace279f70a\nnull\nnull\nnull\na8db965efbb53c12b90c984e6d6a0b7b\nba9d79b41170ba174c7d61282810f0aa\nnull\n2db55b1344f460bc7be3ab61d86f707d\nd10b00873f60618be17b5ae5645e05e1\n44f0916c480e153bf4ba9d3dcaad1108\n00f0aeb67879cbd9785f442cc549f816\naa3b0faece6e16380e02367b2afdd0e1\nf818256487d6935c573d1560376e8444\n2bfd92ccfd38430fe5d7eff19aa2b283\nnull\naa3775a98577fb817e110914865e91f0\n9f2c085c101a79c78284d172876d4295\n20027090a09114cc35d44d650d9a09c6\n20027090a09114cc35d44d650d9a09c6\n6da7c52d1147d9c651a6e0b743a5d889\n6ff08d322cf2fe4666f153f7b345eb5e\n4a2b77dfdd9c6b01b6a8b84566975ccc\ne33d7218e4975b4631cb14907cf3aa4c\n83dc8cb4d59f9d959bcb7453cf17d82b\n82331583a2b02ef1c55b5a4f24937b6e\nnull\nd6d05dd790d686d6857151d5e6e4fbf8\nnull\nnull\nc81e491f1405bbffb3b873ee3d83e053\n466bddd49a8be3ba90fc1046ee4b93f7\n2d20bd5118820a9bf668b7c0c69b32e1\n2d20bd5118820a9bf668b7c0c69b32e1\nc76abba9a952dc83690dfb200834b66b\n936a2be0deedf765af9b47386a719f02\nnull\nccd00cc8d1feb66650c00ae4d41ee732\na1d212e4cdaebb58c8e583b946d1e389\n9c197335d2f522506e07b388c826063b\n5d3676b24a4fc54578cf2fd73b00cfb1\n10dfd37534f83ac3dd94210af4c69d19\n10dfd37534f83ac3dd94210af4c69d19\nnull\n62da0045384b0a4e4af78617576e6f52\ne8de19b5b1c0bdc4a0be32532f8772d0\ncbaf10c66eb422219e390fe03738d67d\nnull\nnull\n3ab977cff3d80a8181085f42b2a5bb7e\nnull\n1de7623f6d1fce03ddfa9313974e682a\nec8957b4bcc4bafd5b23d4eaac21cfc0\nec8957b4bcc4bafd5b23d4eaac21cfc0\nb76122c983bab7fd85e4f00dc2ac0066\nb76122c983bab7fd85e4f00dc2ac0066\na8404ee491916ee854f5f8f70c94e8be\n46874efc7722619f5923fb622976a812\n46874efc7722619f5923fb622976a812\nnull\n65c146991b121bc1204b6dce85c8a60c\n6e8af5788eb401295324082ae0fa4cb1\nnull\n0decd86e79aa32d15b6ce856fde039fb\nde302b8665115035f6d8b866c9572931\nebfc30ed2f43c8cd1dfaafebe4198da2\n1280a5919abae8b5b47bbe23684e2324\n9e58040147fe1ce315a15f06a350c851\nnull\n9c197335d2f522506e07b388c826063b\nnull\nf260ce51844626b7c38d588b072e3bf6\n972288708dd0a38ccab457333293b248\n9ce29da484c48bd3105b1dee849422d2\nnull\na5b8976726d7458abd2f58e18967a331\n93e281e8686ee3c3a47a07701d5dc788\nbdeb1c77893d8893622a897e57a66f0c\nnull\nnull\nnull\ne39a9c7f28ebb174858857531da1f595\nnull\nnull\n186cfbcdf13b371f26915e93dbd09b6d\nba06ea78b338a8ffd20b757d00a7eab2\nnull\nnull\na58126ea455f7d32c58e28a839590a6d\ne450b1d4d6a3c4531979878d838419fc\nnull\n05e096605f47d5d33d9fe364290cac87\na09e3bf400c3633c70a3744ea9cd3df9\n51798b9df22eb51cfd36e35a1358480a\nnull\nnull\nnull\nnull\nb5a253416444fcc2d8e2b3aab48dd009\nnull\nnull\n6c43d420c24d68883a4ec10751d25d33\nc6273805a050876fe62418d82210da43\n0340f1627dfb2576865095c4d935617d\nc20751423f686327c0d2db5c79d5894e\n7e18472d27c859bb7fd8771150cbe3ad\nnull\na1203ed25662811ea2a4348c65ac551e\n0170fe2deaa9486ae35a8cc4e9624f96\n4e3079692a81b7a3c963e2186244cb57\nc5805ae5cbf95aa5e56c3f6ecef8f3ff\nc7bbd005e5d98409590de4e233b68215\nf1c7e38fe93d21578b2f24d4456c1dac\nnull\n2382a14fc139473597877205cc48bc8b\n14649119c8e9f1bf65c6174e0030c175\nacfffa9c9865a8d9cb2b0dc4314f6f14\nnull\n200e3b42dc3b90e19f751ab65b1557ef\n716b78c64cf2ffd0af8d9c91824581d6\nnull\nb4742b73326b3afea6b49687d3a24e5c\n1f06545e3d47a1030fe6b3f46e38220a\nnull\nnull\n2ad26f0f25a614083f5f20b13edce64f\nnull\n9090f4923f3d4280ccfa67a18c7e61f6\nnull\nnull\nc9a394fde046b8cf192bf22d13268af8\nedf8310eaa0c6c1d3069838020d473db\nb7e09a623a9b1491c7b3084c44bf36cc\ne40630447a8eb614ac8b0054c7f85891\ndf8acf7d2d9d61aa6d8a1541b88e6d5f\n0bb9c91914ff46aef0006cbc9515daad\nnull\nb2d8efed04ff861a8247edba78ef373a\nb2d8efed04ff861a8247edba78ef373a\n99ab7ab3879ecfa0738465c51f72c611\nebd6f27d6a7f2beea3886cfe59998c2e\n396ac10ad1d99bf78cf1db45d5dc6272\nnull\nb8569a78a415357240905cf0f4cf2b2d\nnull\nnull\n368fa6f5e03babcd1baee7c60f2f1991\n3c9bac446cf5140b159f5ca3c8e96b2f\n47e039fdf058c73915a686ade5a1440e\n8250a10d0ad54ec8c8878aba00333c4a\nnull\n3502e1a9535ca7fbc6fa24916087e5b2\n3502e1a9535ca7fbc6fa24916087e5b2\nnull\nnull\nnull\nnull\nnull\n40974b27abdea82e0d28102cccb0e5a3\n795302c671bf9647f7bc0e645d5315a7\n2f853926588ef63ebe27a9a64fb85276\nnull\n06d72c54372ea991709f879de0f19681\n06d72c54372ea991709f879de0f19681\nnull\nnull\n801dfeda5a5f7866d6fc2387bed08e75\ndf1b771682a9bdcfa5d95e3bd7747108\n8b93466cd3b43f416057f5545748f85f\n7d225a4606c48afb2325def2e7b09735\n7d225a4606c48afb2325def2e7b09735\nnull\nnull\nnull\n1ff6439a85f75cb8a192804114195838\nfa74e9052a03897bc6cba139e5cfb9ec\n120324a7700301a12c6e25efc6e831d2\n413205bf3ead520594fc0a8b142b9fca\n19dad2e0dd6d72b8d6f15e9d5f244cf1\nnull\n06cad25524b5dcbb570fba5f98e57f2b\n00f0aeb67879cbd9785f442cc549f816\nd67edd4680fdc69190458c119ef15955\n9e42e18b774e3a73754da4c44218e2c4\nnull\nnull\nnull\nd630476119c61a0cb6fad85a81b014d5\n3bd4dad02c11cd197d2a46d561b7cefd\nnull\n92803b364551ffc3ac9c4c3277fac633\nd96dbb335122613fc930d186d551eb52\na668f9ba5f7942c1c759ee248da4014b\nnull\nd89ec02d8f0f573ecfe55fa51a9c6f29\n3cc0a4086dde5dc85bb85356fcf07de7\nf58c76f6036b09f8fb25707f4470ccbf\nf58c76f6036b09f8fb25707f4470ccbf\n76a38b969f20cb3f6d3c8ccd91996584\n76a38b969f20cb3f6d3c8ccd91996584\n76a38b969f20cb3f6d3c8ccd91996584\nc63973fde96ef5d9b93087e951d8eb19\nnull\nnull\n30fecfd98162eb1739a17f34066bffec\n0ba787c897c960a44a5a1635030327d5\nnull\nd16b51994099e5d09d889423b1c5d73b\nd630476119c61a0cb6fad85a81b014d5\n9880278dfdeef443cf380ce0612d6286\n413205bf3ead520594fc0a8b142b9fca\n588a88cc1d461b7fbbf37fe0db730c93\nnull\n49d3a55affec7a1c5baea0120b4468e4\n17da4e2d3393a044093a229d56655e71\n774ab5aafe9ed359df44ea71ffec92ce\nfd9448260742d9b140658cd3a1c7dbd7\nnull\n0692430d2d34ce02be37f1b54d661924\nnull\na0b02a506d00d0863a2d43573a3f39af\n6bf41e12763f82cd5a1142dc6948640b\n2504c51eda96c43579547bfddd10037f\nnull\n304911cba6b9d457715d92607ce763a7\nnull\n70738905edef0d432dce679041012432\nca355d1e31083677d97374fae9b09526\nnull\nnull\ne2d14bb37bd1feaa7e583caaf44f00b7\nnull\na1db363d8803a027809e9711d7bc39cc\n2a449bb8147128b95d2b69a4d9579da9\n5718634b88600e57f6df6f06b47a4054\nfbcbd91f7291782371d8b944297a140b\nnull\nnull\nnull\nbbba7ff572cb26b2007755b44434c805\nnull\n129fceb06e84f2339bdd61e38277160d\ndd03c139c0970e0499e2ba3fc871404a\nnull\na311bcb3a9810b8656858cb72f10caf3\n1f51ed27e3e9c9e70d81f6e22ceb2f32\nnull\ne3dd09406093e38f98a92a2c287424c0\n1fcc78384c5d34de84a6807e463fd5df\nnull\nnull\nc2ce39e64b3d8bdaa32c8350ecbff92f\n5b8fd67269d8ff9436ea272eec4556ff\nnull\nbee7fa3ecb6b120b7546f6a0f487e3c9\nbcbfdb9fe840467c2d61ec118a8074cb\nnull\nf7db8b6a21c2be0b004ace3abc6cb762\n08f157ed46ee6ab89a0512796801ea79\nnull\n65534763de48b027aca6224a1a36ba23\nnull\n659d77b5a46bb2795841c18dfd9e82c7\nb9903e5f410cde5582c33457ee194707\nnull\n215b6b9ed79a40cd425af86efb18732b\nd76e758263c77fa21455a9ffcd3381e8\n6101c47b377ce759af7244b59631e073\nb8142c21a50c19bd60bff836cd1e55a4\n1463419ee17c339fcde15084a4523926\n7f7737f2f9fb4d377c2227824a01fe8d\n95355399915a79a4131e4bf48f60f171\n95355399915a79a4131e4bf48f60f171\n95355399915a79a4131e4bf48f60f171\ne7378bfce6887838733ae76635263da1\nb5d690d17a6c6d0d8b7f9a58bdeafe70\nnull\nnull\n4d925252f48cf73f88507d07043d32f3\na26665541b9f3300d3af36dfba589d22\n7f79d9b54bd67a2d4da5d05bf4f18146\nc824605062afb7bd1ecf0d3700c7c769\nc824605062afb7bd1ecf0d3700c7c769\nc824605062afb7bd1ecf0d3700c7c769\n5426464d5efc0cc80003db96973815aa\nnull\n4ff6f232a81113592457f4af07880fdf\n3f782f70e8b9befaed870646abcaa57f\n3aa749c49f4ca7c7fb762704aace2aba\n70949e3f74e642d8260986ac0567d394\n118b5b596c05718eb0a9661a8529b32d\n118b5b596c05718eb0a9661a8529b32d\nnull\n694da1a14e588d780aa3154c6269476b\nnull\nnull\nnull\nnull\nf94e70a641add70a12c57c57a02777f6\nf4f3ff92cd960f9efdd8272673ac8b2e\nbc9ef4bcd26718d3d3cfdd4884d512e9\nbc9ef4bcd26718d3d3cfdd4884d512e9\n8e7c15f37521c432b7c226aa0cd55e38\n4dc503da5238f91ced7f77bf59f92a61\n1c393c9804fd8ada93ed8050c195d4aa\n96b0ca43b47bcf6beb3cd7719ad88115\nd65cd120fe12c7411cc99e936f434c3d\nnull\n8cdf0c5adf6a5f69c3d3f82a86294e3f\nnull\n066c6c36fed2faf38a8fb5063e09d881\nnull\nnull\n8cdbb5a7111910c09c2bbd2e582fd033\n7762d036250120be58fc009d286045dc\n72edcacb5c2545304f4237f567b95362\n62e1119e9f7956b41326e99bd3f569f2\n040e5e44a6803973c56de89baccd4052\n85d16a679bc1f272429ea57a27d76304\nnull\nnull\nac76bcabf79d21841ede34c9aeb59fc1\ndbeef3e30b3c49a8c302a749cd1df9a0\n6e1f68829191f2e812885da1b449ffa0\nnull\nnull\n349e01eb4e28a13476e483e6dbebaa16\nnull\nnull\nnull\n97bd6eebb66b293b3129c77d0b842d8e\n086b9f57f99f3208717f93852b511a48\nnull\n0120a2616c3350991e578d0954065049\n1b03a97ff55d63c7b3bc2c0d0a6e95a0\n4bcc474dcdec1cf2587197e5d72b0df1\nbf3b16d30e8ffb5858da90ac96652157\nae9c56b4fc394a2a6c0cf54cd3ea8474\nb0a64d57ae8ba6afffcd56b92f0a1eaa\nnull\n610d4c7c320fae7e3ad4bc6786e8b9fb\n800bddf77f86b96022b51c6c936e0c12\nnull\n0d7384989f3fab012be2aaefb9fdcb59\nnull\nnull\nba06ea78b338a8ffd20b757d00a7eab2\nnull\n257eed66c7e81798cff273469d2f3732\nnull\n73cd3a644825dcab9195d2eccc506565\nnull\n51fc5da05e15c4c1c0327690c66381ba\n7d7d22928d914468512e6e9001837f82\nfe6704c8175faf565a5a10c12ff8bc3d\nfe6704c8175faf565a5a10c12ff8bc3d\n86901c26598da1c7dc027b6997cc1b2c\n0d44548a3b99a1a891540a687467209e\nnull\n0d44548a3b99a1a891540a687467209e\n3061a4fd1d6393707d68f7d587a3d45b\n937a1c0ac6f02e0c7992f586fcfb4b53\nnull\n2a8ac3f4a4e22f5f7b849cb4c48deea2\nnull\nnull\n1bc0384d8273afe08012a98d105f81da\nf9f6c1bd491c38e668d958b19e2ead31\nf9f6c1bd491c38e668d958b19e2ead31\n9ec24a3cd480dc51bac3f44bc94dde1c\nnull\n348e28714d5dc41c723144ca6e33aa8e\n51e3f563def781c98890531494b54826\nnull\n3ba895801dbf2dcd4cc510711922215e\n386939ec1f22de744f22f34ce7537532\nc194f9588cb472a99e8e3318982e556e\n99fab79286f51dcfffb5c54daf1b750d\nnull\nnull\nnull\nnull\nnull\n99467f70eeee8a1d42b954bee01c2a2f\n9894e68927f07a42c2bb7ab630675856\n7e79e9816a1b32b41ce37a54e90d2760\n07dc6029b1a5678a19e3614af262bade\n3a29401ec8d9d79e8a2c9b9eb675a413\nf3a2d38c51f5404b40a68bdab4e5f9eb\n331e4b355e6ab970af300a4444d11267\n445b7442f791272b480a4a8c9a9591a7\nnull\nnull\nnull\nnull\nb13d6930d802a2d58a36fa5c6eba5eae\ndc2f38b5da594542ef816a2cfa35b9b4\na0aec9322a6392c7bec52f73ec03570e\nnull\nnull\nnull\nnull\n03f14b14c92ba4e02d16706597db124f\n14b13f228a26e5904fb941a08b1a5bfd\n14b13f228a26e5904fb941a08b1a5bfd\n54602073f3e97703f12df3fe42c488de\nnull\n590e6a210d1e040cccb065841994118a\nnull\nnull\nnull\nde860257ca3b96109888a4088226371e\nnull\n4dcba34d28a3ca14c2e70cdb2ad9aa59\nnull\nnull\n9cb45ce481ba9350f56da260bbc8c28c\nnull\n862c04b2aba243768509e60aa42c9fbe\n2ed064852c5f37d2c677a7a2b3642eb2\nba8d827dd79cbc119f539a8b98b96c4e\nnull\nnull\nnull\n3ef2e433f9810186f3baccf49e5d2487\nb823010a5d464e32661830d9f62fc359\nf7739d7858000b5fbfbf441e64c6e5f7\nnull\nedbcd8f2daf67054bd755813acf6b8d3\nnull\nnull\nnull\nnull\nnull\ne2c072e2b5c0a6e5bfbf61182012c9a0\n0dea993bce2aa2d51f91f45bfc642115\neb108ebaea188d515a4227129dfe2f9a\n0dbc9d331819efe1336514f6c66899f4\nc469a23e783c97fdb72310feee19afdc\n826ed080926d70b97c7e511726587e6a\na16760186abbe4dbbeaa2b0afd79f040\nnull\nnull\nnull\nnull\nfe03c425ee1fe1731b4102a013fd0a1b\nnull\n074173e44c23f102fc50f9218b45abc4\nc6a16598cbec75545fcd190436c0892b\n1d05573275a5231c6630edb8a21a0bdb\nnull\n2249eabdd591cdf6d3f1d9fbddfdd10b\nefd1c3eef9ab3ba6a73519d0723c4db2\n8346362bfbcae18cdd5035a6a793a88f\n8346362bfbcae18cdd5035a6a793a88f\nnull\nnull\nnull\nnull\n93e281e8686ee3c3a47a07701d5dc788\nbab2b39008ff64ac80b8cc12a09a0c6b\nd2c488cad3786156001d4bdad8ae414f\n074e933b6ea10cec76d445f008e1976a\n074e933b6ea10cec76d445f008e1976a\n91db484eda9b33c2d92198ce0bc7d299\nnull\nnull\ndcecf53f5e6ac4fc2a73eeeaf109c362\nfa4d5ef8987ac397dcc9e91a5d92a02c\nnull\nnull\nnull\n818c6f8109d480a5af7b61efb4bb15a0\nacb7eabc67337010eef49bdd87ed9b82\nf297ac0d300a9b9c14c54a36121eeaf1\n0e285b2030bd4fffd012bc6d85063bee\n0e285b2030bd4fffd012bc6d85063bee\n4f81d37a458d675b7aa9240c55d2329a\nfe0e346dead60a7a7271708dd53baa81\n064a2d5ca0c12b4cdff8b8be6efdad1e\na311bcb3a9810b8656858cb72f10caf3\nnull\nnull\nnull\nnull\nnull\n7edb68d347c2a06daa4304eca73602c1\n1129d3f09b6e0048bae1ae392083f7bb\n73577d81e9c4b38dba716b9b873db846\nd74a6133d14966c745c3ac016c1c8d67\nnull\n6f18b0ef1c30b498f1b5ae20b008ef38\nd9594eda16a5e2ec1e34b424afd2703e\n13b873553e617daea1a5f66693bcdff1\nnull\nnull\n90cecb44a6ec54bbe1a50687a4f37daa\nnull\n0f330891e1185524105fc02469a49430\na2916588a2b9d41c9c055fa6e05e4cef\nnull\ne2ebed9bacb56b8ffefb2697613f8cdd\n8c798599fac575f4c0132b13d4317088\n33ebf2025d345320681cacbc923e9c55\nnull\n0bd7685e0a3208a4456e924e93a8cf73\n68c39cb7b12466989e23d1bdff9df43b\n4c781bf1b0aad3b4475139c3a4c4775f\nfc674c68722305d350ad74050ac81d00\n91c8e8624fefd37eb6d65ae2d9f84df9\n4e78b4002d887d90b0081e27ac2767a5\nb68f5731760394492bb9d6884230562e\nnull\nnull\n1b23f4382d12aa56c387d1840d452d98\nc51ac3bf89beb1a1d7481e77fcff1934\nnull\n42293afc211da8fcc2929b23c334ec9c\ne75ba239554b99fda7f5ac38d402f1be\n2b6cab6213766b399b3a96b67afa0a29\nnull\n108a0cfab81386ec6bb994ca5acee196\nbb27ed95fc23da886bc8c2578b8370a5\ne5d4cf0905ca6954c09a7fec99fcf169\nea0ee99b374f9ee1b0a82ba3d36378e3\n1c390dd3ce9a85bcf20eefd2cf561795\nb1279934823c4b6dfbff7b3a60e30995\nnull\n07b69e50d39fddf564ef766e3ad54955\nf51d5f6d7343fc4b28577fa633d98e84\n473e4c68540e7d119a2394a3b0796121\nnull\nnull\n4912113edbb4434faf00b89b882e1758\nnull\nnull\nnull\n67f678e7c6da1fb02eaf5c3c7b5e359a\n289fa98d316b8f2d2383eada93ef67d5\n3713d368348cffd44b134a7340e747b4\nbca5c342b5ac655494b557e9da545480\n0fac063d00e7e65cccf71d019919eeb0\nb90b07a8f83a075e05e2037919b77e5f\nnull\nnull\nnull\ndf720ad63e53c268d5f55ea419b1249d\n01ced69f3238f5adafb49cdf31cab668\n01ced69f3238f5adafb49cdf31cab668\nnull\n34ea0742cec37ae9ea70e1965592f178\n6f7d88b6cf563f856eb22603ed6c8e6a\n0283095be13f656217870f392570b3b9\nbc5b1b36c1fcc133252d25619e58ab99\n167c6700b236f3355c53a0a1115ae9ee\n7065ab876ba455bd8f8dbbb16703f3ed\n741cd0fadbace7507f26ed9e998b778a\nnull\n74c9fdb2fd51b73d644f981f0dcca8a7\nb31654dbeae1bd8c364918f91ce2a69b\nnull\nnull\nbab812421d392b07d898520f73bbadd0\n7410646ab24ed45106d772e57a556b50\n7ae651c2c901a3b68b46a91327b7ffe6\n2123f73612ae518871f59dd33be85a79\nf01a84eaf505e21e08601e243e467665\neec801fb8f47e6a4d268462dd7766e7b\nda82b7bf8de314ad6d5346ecf52a21d2\nnull\nnull\n87017b6accb82db55ee166d14bfb6ad0\nnull\nnull\nfa8092e288b6e676bad8ae2c1bb06589\nnull\n758763cbe42e04f1e7ce1157ca96b9af\n6a4c6387abcf8930827e95e3c028d689\na3bcddd2c1f915a4764302dd3734aa09\ne8de19b5b1c0bdc4a0be32532f8772d0\n8495ece822ab35925a2a3fdc502912cc\n124316355b5ee34d17d21ff97ef17f74\nnull\n3f66886ad877c8a2c960f7c7990705b4\nf7db8b6a21c2be0b004ace3abc6cb762\ne29c823c0c162933739388c8e4901468\nf906065e53eb4660d79e49dd8462d9ad\nnull\ncf41fef2559c3e97269f005c3f0caca3\nc1b204e5fb061b3132907a126179654e\n2099b14c345691e393c1a25c5dbeae54\nf3a2d38c51f5404b40a68bdab4e5f9eb\nnull\n204dbf19e7592fa5bfc852fd5030f024\n31259afd3542ecc5d70a68504a4a7965\n936e5c6751cecba47f5b483b3febb8ca\nnull\nnull\n3fbacf3e8f206c07eece7e3cb59a46a6\nnull\n89321a7236a97af817ef82b70a452ca2\n69a39693048fccac36f206abad898485\nnull\nnull\nnull\nnull\n4906d7ae2f3b18b7373d895343f46baa\n282053d62919af5771cbe4c7e5360dd3\nfc1f445a7733aab1669161e317e838a4\na5ea7ced473854721e69b0fe8621dfa4\nba7a4d349dc57d693bee12deea691df1\nnull\nnull\nnull\nnull\nnull\nnull\nf90395f3753f2af0d681e7aa3e4ea5e5\n139d47a51cbe1a47c9dd1bd3b1cbba19\n2a0152f7fb904dfc763460c273e58aaf\n2a0152f7fb904dfc763460c273e58aaf\n051a94fcfeef49c1315a8216619698b0\nnull\ncd192ac95e0b0fd05990665ddb875ee1\n329032efe60ebe43aaeaa023846fc4d2\n329032efe60ebe43aaeaa023846fc4d2\nnull\nnull\n28c98caa50df041a67394f2e7812b8c5\nda29762616c23e037e36061271c09fc4\nnull\nnull\nnull\nnull\nnull\nnull\nnull\nnull\nnull\nnull\nnull\nnull\nnull\ncd52eb24da705216dba3e215dd50413e\n2db1608d77e0227cebdcb18a0d626058\n413205bf3ead520594fc0a8b142b9fca\nnull\nnull\nnull\n4af9af3629d68e1a355d73bfd5bf4c57\ncf5a24a7129cb8808340b905bb7a22a7\n4e3e3633bc2bfa51b69d6b1e246ed34e\n10283f91acc07b148fb621b05e86e36d\nnull\nd8e5d11d41052790b3a5e6e6da880ee6\nnull\nbf59365886a375870222d7d84450331f\nnull\nnull\n8d8c6af1ff9a8b96f34e5997dd18623e\nae9c56b4fc394a2a6c0cf54cd3ea8474\ne860c1f8e9658141b09ae699a4010437\n18e0cb9244b37e2ba13fa1706f87234e\nnull\n00de169eb92fe9a22baeced573c628b7\n7315e1e9bd6bd96c1d38988582e67c3c\n7315e1e9bd6bd96c1d38988582e67c3c\n1390e4280db151fcc679b0fed7ccf054\n383f90cfe6e0f0bc2362c18fe44ccd13\n4b99d08611cd518950243894d9ec635f\na01e72294b306c3e67febfc8d79fe75a\n9a432cfcb8f7ceb75a0068b5198f1e93\n4e87119439e4d7d262fb98370c010eb7\n4e87119439e4d7d262fb98370c010eb7\n0a7c8acf904040dc95ce3120d4d901d3\naaafd17a4eac221e183929bdf449cad8\n6a55fd92ce4c9e4174c8162e28c1b773\nb52b4a96b9384f7837e81b9d902fd045\nnull\n705e42914a1711695be662e19e5ae3e4\nnull\nf1fd53b557d7e34662b10cb238906c0a\n56210e2cc7f184ae704c7072c16fcdf7\nnull\n6e157ce666c9f1b6959a64f949434262\nnull\nb7f43c1c25371abd8a78f5f5f7b7a1de\nnull\nnull\n0a12d7f930838e82cd80778334ceaf97\nnull\nnull\nc29c5c4bcf9b4776eaf6b1d06fbcfbc0\nnull\n1f6713dce24e151b5acd6a4ce917e177\nced04936bc42806ae23d8920ada2b5d4\n5d6eda5b81b1102e8285d5619be7b4b3\n2f3438f4cba234b8c0d5623966098f57\nnull\nc3123c13a829b288bdb63b983723fe15\nnull\nd39f68ad2ce30dbb83e0fec68bdfb2fa\n64383e87c46c3cc7c0b21933b2aa12c0\nfba48bdd95caac9a52cabf88412124aa\nnull\n0c75686cb91ea2425ed10432f9478b28\n36d87eb94fa6d256caf27746f5cdf030\nnull\n08b458dde3ed54c65660f39741cf5e39\nd1bd0e8d7f35be1dd38cbb7830428f52\n155607270a579ebb013879201896d548\nnull\nnull\ne271a1bb32f9db0d911824d87bc0ac06\n284c561b21b2f744d5a0135403137c2b\n4632255aef82f9811245f650f2af27d6\nnull\n145c0be547a94469e23db19d22cbea77\n3d0dbb64f56f269a4d8396384c90873f\nnull\nnull\nnull\nbb65dadc5262110fd821b94d9396865d\nnull\nnull\nnull\n8ad6191c8555eee0faeec36caa8f1674\nnull\n74f46984846ec7eec470cda857aac2e6\nc768199065468a68c53c7e7c85c7cc52\n783d56b912e146ce0c3b359bc337e95b\n783d56b912e146ce0c3b359bc337e95b\nb264a50d1d018c2539b64a679b9eb60d\nnull\n2123f73612ae518871f59dd33be85a79\n4a1b7f4435cb08dbc63d96edd7e98eaa\n04e8eb446801a081ef5e8f4dba1f8582\nda8a0107b26a64a7ea3efca16261b5bc\n413205bf3ead520594fc0a8b142b9fca\nnull\ne353626e31b94f8bcffecc25ccf1a999\nnull\nnull\n5b78decc15e899f7e8bd3d943b4684a1\n0c5aa42e2d3bb01affaaf10fe0b5ddc2\nnull\nnull\nnull\nnull\nnull\nnull\nnull\nab96f3db33431a0a7c3c2640bfb2f15a\ndc576413c90f7eda9e48928a2ba4bd7a\nbdc8aa301e98347b50277ff8dae93950\ne4a34821a005117686aef3a821b66222\nnull\n0c269cd7f9b40f0cddcd48a4a849bd87\n635580e2be08cf180efcbb0e884fd2eb\nnull\n1e57c133e3bd854b62e444ef034dfff8\nnull\nbb16a73048d1a022d45a354b31b2cf86\n94d9f14d8db8bf1287ff3684c1b34df6\nnull\n750ca2a267d294d6a88c7886de071bca\nnull\n647b7f467cf6e7a266dae75a5cbc6e9b\nnull\nc8f7b1e53010425f08f209c969de20b5\nnull\n88f10e908d274e89eb234730dc26c8ae\nd355eeabc0f736ac42d92c768085c483\ne5f3b4a0d0a818a7e2bf9a43774cd58f\nnull\n6b79a6a9218e2c0c7d8eb838fdc0680b\na42a11d2aeb00e0775a623c1c5c5275b\nnull\nnull\nnull\ndbca2e0713cd6584f2f26a4a2ad74652\nnull\n8e23b1680a5b30b9c94502bc4e23d1a7\nd16b51994099e5d09d889423b1c5d73b\nnull\n6e97bc346824266b74e917f8d43c4911\nnull\nnull\n2368e2028c1d6d2b5da1117692fbc24a\nbddfbd90552887ba6df8b943e363f247\nnull\n1c393c9804fd8ada93ed8050c195d4aa\nnull\nfa1e57ca0630cb380b7e4e4829019140\n68dc6dc2df3a0e81e6cf283387e6107f\n2a756daebd277b62ee0ae45d2cfcbcc2\n953b31717860fefafca7b1c6342f6592\n6816434391ea0a7ba8fde4fca05f749a\n80eb928f549672f5cc04c4d00ee91bee\nnull\n16401c69c57a9c1d765e8ada182c54e7\nnull\nf5acdfa45c186e7bc7b16cfd5d71c5f8\nnull\nnull\nd96dbb335122613fc930d186d551eb52\nnull\nbdb462f8531bf705c033a2f62511a13a\nbdb462f8531bf705c033a2f62511a13a\nc29dedda4c7ffafab14ec85387a0b1b8\ne7fdf81550b1d592e3ae40631701a90a\nnull\nbcbd436269d8f6a4ad2869bbea43a767\n01eef17f8ff030cf86cd161fe053bf09\n8cdbb5a7111910c09c2bbd2e582fd033\nnull\nnull\nnull\nnull\n779ddc265c295f1b2d56013471aabec6\n19ecc33e4c086a3fe36cdce89f65ba80\nnull\n72b3f3544e98088e5bd5cd8fb9f730c3\n07ba2d3cee336a71aab1b793fb81eb33\n125d821ee2cfa3a56386dcdfd3d7ac87\nnull\nnull\nnull\nnull\n96b8ead8c3e4ab8c68962aee156319af\na803d4fc0cacd588ce43a1808222c650\n23763152909a88a9565ed16d750cf328\nnull\nnull\n479309342806d536b0e62138ad0fb9c9\n8eb155bacb56d0131ee704634d16e66c\n6c825e99a534fdee7b12183003343a3a\ndf11e998d84a66d91229306e394e9a5f\nd0f11793df9ec29239f54e3b3087980d\nnull\nnull\n262f2b1d63dab6c65b13d1cb3c3af458\nnull\nnull\nbdb462f8531bf705c033a2f62511a13a\nnull\nc9d76291fffe74b23132060c1386f5e8\nb20ef6c52189cf74bae017ebdd59f94d\n0c42fc42f52537f26e345cce569da7fc\nnull\nnull\nnull\n46e517358361c0db5ff345ca470a8450\nnull\nnull\nnull\n005d6adf64e828162187152bde8e1cab\n77b5c0372fb0d98cb0805d417d463a73\n32a487ec2428f55fb32694341dae063a\na26665541b9f3300d3af36dfba589d22\ne653f83dfdb9223ea8cf1a8a7cd813fd\ne08c46142938f7834bd3632ffac7b8c7\nnull\nnull\n69d66f25945a5f7ed56c44a8d2a0258c\n96480b0a1ca26cdcebf1ec040daee004\n797f0a00535398ddbf3220a2b74fd76b\nf9dcffc7846dc37c1a4c42819e44b7c9\n99fab79286f51dcfffb5c54daf1b750d\nnull\n3ace7f9e0d8e7abe8ba24dd551971309\n3ace7f9e0d8e7abe8ba24dd551971309\nd3382e27d22b92f48a077561ff8b60ef\nebdeae508e05c8f10f30a33b7774823e\neda7cc0bfcd666e9ee60c4dbcc49b772\ncce92243d7ff6283ab889fe7de9c4d46\nnull\n2a333ce129be064bb9dabbece2888971\nnull\n13ca8f578efc84bbb45e9fa7a0bd3a2e\n\n\u003cfont color\u003dred\u003eResults are limited by 1000.\u003c/font\u003e"
      },
      "dateCreated": "Jul 3, 2016 9:40:41 PM",
      "dateStarted": "Jul 3, 2016 9:40:51 PM",
      "dateFinished": "Jul 3, 2016 9:40:52 PM",
      "status": "FINISHED",
      "progressUpdateIntervalMs": 500
    },
    {
      "text": "offerViewId.count\nofferId.count\nparquetFileClick.count",
      "authenticationInfo": {},
      "dateUpdated": "Jul 3, 2016 9:50:53 PM",
      "config": {
        "colWidth": 12.0,
        "graph": {
          "mode": "table",
          "height": 300.0,
          "optionOpen": false,
          "keys": [],
          "values": [],
          "groups": [],
          "scatter": {}
        },
        "enabled": true,
        "editorMode": "ace/mode/scala"
      },
      "settings": {
        "params": {},
        "forms": {}
      },
      "jobName": "paragraph_1467574836551_-991024038",
      "id": "20160703-214036_1152893633",
      "result": {
        "code": "SUCCESS",
        "type": "TEXT",
        "msg": "res23: Long \u003d 165668\nres24: Long \u003d 165668\nres25: Long \u003d 165668\n"
      },
      "dateCreated": "Jul 3, 2016 9:40:36 PM",
      "dateStarted": "Jul 3, 2016 9:50:53 PM",
      "dateFinished": "Jul 3, 2016 9:50:55 PM",
      "status": "FINISHED",
      "progressUpdateIntervalMs": 500
    },
    {
      "config": {},
      "settings": {
        "params": {},
        "forms": {}
      },
      "jobName": "paragraph_1467575438570_1998343577",
      "id": "20160703-215038_1910307135",
      "dateCreated": "Jul 3, 2016 9:50:38 PM",
      "status": "READY",
      "progressUpdateIntervalMs": 500
    }
  ],
  "name": "KelkooData: offerViewId-\u003eofferId",
  "id": "2BQSZXT4V",
  "angularObjects": {
    "2BGHSKCA7": [],
    "2BFMBPKAB": [],
    "2BHKKP27G": [],
    "2BJHJDBK6": [],
    "2BJAQG5W4": [],
    "2BJGSXM37": [],
    "2BFXEV5XZ": [],
    "2BG77RV7M": [],
    "2BF969NNB": [],
    "2BG8QQJNC": [],
    "2BGVG5JP4": [],
    "2BJ5FCP57": [],
    "2BFEDXCTE": [],
    "2BJ8AEWCT": [],
    "2BH9AVVKH": [],
    "2BJ7KKX85": [],
    "2BHKAE8WK": [],
    "2BJ6HN5AY": []
  },
  "config": {},
  "info": {}
}